{"name":"NewFeatureType","type":"FeatureCollection"
,"features":[
{"type":"Feature","geometry":{"type":"GeometryCollection","geometries":[{"type":"Point","coordinates":[-75.914642,41.221193,0]},{"type":"Point","coordinates":[-75.9135309,41.2248041,0]},{"type":"Point","coordinates":[-75.9179754,41.2214708000001,0]},{"type":"Point","coordinates":[-75.9610322,41.2420262000001,0]},{"type":"Point","coordinates":[-75.8786029999999,41.248118,0]},{"type":"Point","coordinates":[-75.9919215,41.1932369,0]},{"type":"Point","coordinates":[-75.8883297,41.2432037,0]},{"type":"Point","coordinates":[-75.9467228,41.2409514,0]},{"type":"Point","coordinates":[-75.955022,41.2381848000001,0]},{"type":"Point","coordinates":[-75.9000243,41.2623724000001,0]},{"type":"Point","coordinates":[-75.9343003,41.2352466,0]},{"type":"Point","coordinates":[-75.9393077,41.2436944,0]},{"type":"Point","coordinates":[-75.8885177,41.2703920000001,0]},{"type":"Point","coordinates":[-75.8897929999999,41.2406933,0]},{"type":"Point","coordinates":[-75.8910228999999,41.2680415,0]},{"type":"Point","coordinates":[-75.8910228999999,41.2680415,0]},{"type":"Point","coordinates":[-75.95107,41.2427200000001,0]},{"type":"Point","coordinates":[-75.96603,41.23328,0]},{"type":"Point","coordinates":[-75.9052053,41.264151,0]},{"type":"Point","coordinates":[-75.9081166,41.2371644,0]},{"type":"Point","coordinates":[-75.912546,41.2328632000001,0]},{"type":"Point","coordinates":[-75.902306,41.2787541000001,0]},{"type":"Point","coordinates":[-75.8885285,41.2407359000001,0]},{"type":"Point","coordinates":[-75.9081672999999,41.2390201000001,0]},{"type":"Point","coordinates":[-75.89141,41.2615655000001,0]},{"type":"Point","coordinates":[-75.9108514,41.2404721,0]},{"type":"Point","coordinates":[-75.8833399,41.2341000000001,0]},{"type":"Point","coordinates":[-75.8871416,41.2568025,0]},{"type":"Point","coordinates":[-75.9495623999999,41.2140821,0]},{"type":"Point","coordinates":[-75.8748432,41.2387953,0]},{"type":"Point","coordinates":[-75.9474499999999,41.2398900000001,0]},{"type":"Point","coordinates":[-75.9331835,41.2357265000001,0]},{"type":"Point","coordinates":[-75.9331835,41.2357265000001,0]},{"type":"Point","coordinates":[-75.8841556,41.2406421000001,0]},{"type":"Point","coordinates":[-75.9495216,41.2403989000001,0]},{"type":"Point","coordinates":[-75.8913176999999,41.2399118000001,0]}]},"properties":{"UserName":"AndreaL","_count":36}}
]}
