{"name":"NewFeatureType","type":"FeatureCollection"
,"features":[
{"type":"Feature","geometry":{"type":"GeometryCollection","geometries":[{"type":"Point","coordinates":[-118.3268521,34.1498332,0]},{"type":"Point","coordinates":[-118.3618604,34.1868849000001,0]},{"type":"Point","coordinates":[-118.3192559,34.1521948000001,0]},{"type":"Point","coordinates":[-118.3407358,34.2071891000001,0]},{"type":"Point","coordinates":[-118.3411201,34.1958422000001,0]},{"type":"Point","coordinates":[-118.3440169,34.1625672000001,0]},{"type":"Point","coordinates":[-118.3083773,34.183366,0]},{"type":"Point","coordinates":[-118.3363134,34.1796583,0]},{"type":"Point","coordinates":[-118.3125679,34.2006489,0]},{"type":"Point","coordinates":[-118.3208822,34.1682926,0]},{"type":"Point","coordinates":[-118.328749,34.1567701000001,0]},{"type":"Point","coordinates":[-119.155627,34.2163699000001,0]},{"type":"Point","coordinates":[-118.316824,34.165354,0]},{"type":"Point","coordinates":[-118.3515885,34.1809192000001,0]},{"type":"Point","coordinates":[-118.3206875,34.1733142000001,0]},{"type":"Point","coordinates":[-118.3451449,34.1887043,0]},{"type":"Point","coordinates":[-118.3204165,34.1982064000001,0]},{"type":"Point","coordinates":[-118.3351998,34.1986413000001,0]},{"type":"Point","coordinates":[-118.3370071,34.1787860000001,0]},{"type":"Point","coordinates":[-118.3466151,34.1806990000001,0]},{"type":"Point","coordinates":[-118.3116472,34.1947280000001,0]},{"type":"Point","coordinates":[-118.3363014,34.2105409000001,0]},{"type":"Point","coordinates":[-118.306801,34.1904361000001,0]},{"type":"Point","coordinates":[-118.3265949,34.1634586000001,0]},{"type":"Point","coordinates":[-118.3055157,34.1851005,0]},{"type":"Point","coordinates":[-118.3340459,34.1777318000001,0]},{"type":"Point","coordinates":[-118.3481922,34.1879322,0]},{"type":"Point","coordinates":[-119.1814149,34.2202838000001,0]},{"type":"Point","coordinates":[-118.3096646,34.1805214,0]},{"type":"Point","coordinates":[-118.3520571,34.1524007,0]},{"type":"Point","coordinates":[-118.3056096,34.1842472000001,0]},{"type":"Point","coordinates":[-118.3539108,34.1963255000001,0]},{"type":"Point","coordinates":[-118.3088927,34.1833596000001,0]},{"type":"Point","coordinates":[-118.3339123,34.2104695,0]},{"type":"Point","coordinates":[-118.3086883,34.1833658,0]},{"type":"Point","coordinates":[-118.3271746,34.1699834,0]},{"type":"Point","coordinates":[-118.3136133,34.1872203,0]},{"type":"Point","coordinates":[-118.3080692,34.1820239,0]},{"type":"Point","coordinates":[-118.3567422,34.1384668000001,0]},{"type":"Point","coordinates":[-118.3095793,34.1605202000001,0]},{"type":"Point","coordinates":[-118.3078412,34.1543233,0]},{"type":"Point","coordinates":[-118.3270244,34.1546785,0]},{"type":"Point","coordinates":[-118.3209787,34.1688827,0]},{"type":"Point","coordinates":[-118.3185647,34.1726641000001,0]},{"type":"Point","coordinates":[-118.315963,34.1783227,0]},{"type":"Point","coordinates":[-118.306999,34.1820283000001,0]},{"type":"Point","coordinates":[-118.167551,34.1613015,0]},{"type":"Point","coordinates":[-118.1601212,34.1391088,0]}]},"properties":{"UserName":"cycleloco","_count":48}}
]}
