{"name":"NewFeatureType","type":"FeatureCollection"
,"features":[
{"type":"Feature","geometry":{"type":"GeometryCollection","geometries":[{"type":"Point","coordinates":[-118.872869,34.2836707000001,0]},{"type":"Point","coordinates":[-119.0017673,34.1844499000001,0]},{"type":"Point","coordinates":[-118.836624,34.3000185000001,0]},{"type":"Point","coordinates":[-118.879467,34.2255507,0]},{"type":"Point","coordinates":[-118.867945,34.2182805,0]},{"type":"Point","coordinates":[-118.8985277,34.2664158000001,0]},{"type":"Point","coordinates":[-118.8780291,34.2857068000001,0]},{"type":"Point","coordinates":[-118.8220874,34.2504864000001,0]},{"type":"Point","coordinates":[-118.88184,34.28704,0]},{"type":"Point","coordinates":[-118.8851813,34.1848116,0]},{"type":"Point","coordinates":[-118.9948251,34.2239774,0]},{"type":"Point","coordinates":[-118.8820941,34.2071703,0]},{"type":"Point","coordinates":[-118.88073,34.27932,0]},{"type":"Point","coordinates":[-118.83465,34.2475900000001,0]},{"type":"Point","coordinates":[-118.8803746,34.2858357000001,0]},{"type":"Point","coordinates":[-118.885022,34.280316,0]},{"type":"Point","coordinates":[-118.8920992,34.2681752,0]},{"type":"Point","coordinates":[-118.8866826,34.2835126000001,0]},{"type":"Point","coordinates":[-118.905267,34.2651738000001,0]},{"type":"Point","coordinates":[-118.843618,34.3001861000001,0]},{"type":"Point","coordinates":[-118.8757325,34.2678177000001,0]},{"type":"Point","coordinates":[-118.8804311,34.2809984,0]},{"type":"Point","coordinates":[-119.033135,34.187847,0]},{"type":"Point","coordinates":[-118.8789175,34.2438251,0]},{"type":"Point","coordinates":[-118.8651805,34.2706549000001,0]},{"type":"Point","coordinates":[-118.8336696,34.3008091,0]},{"type":"Point","coordinates":[-118.8305677,34.2708862000001,0]},{"type":"Point","coordinates":[-118.8305677,34.2708862000001,0]},{"type":"Point","coordinates":[-118.8661026,34.2692793000001,0]},{"type":"Point","coordinates":[-118.8860997,34.2877142,0]},{"type":"Point","coordinates":[-118.8741598,34.2834735000001,0]},{"type":"Point","coordinates":[-118.8833351,34.2875593000001,0]},{"type":"Point","coordinates":[-118.8993425,34.2703429000001,0]},{"type":"Point","coordinates":[-118.883893,34.2851925000001,0]},{"type":"Point","coordinates":[-118.8690443,34.2114152,0]},{"type":"Point","coordinates":[-119.0078539,34.2179628000001,0]}]},"properties":{"UserName":"Doug Graham","_count":36}}
]}
