{"name":"NewFeatureType","type":"FeatureCollection"
,"features":[
{"type":"Feature","geometry":{"type":"GeometryCollection","geometries":[{"type":"Point","coordinates":[-119.1382493,46.1967978000001,0]},{"type":"Point","coordinates":[-119.1796572,46.1961155000001,0]},{"type":"Point","coordinates":[-119.1222959,46.2088856,0]},{"type":"Point","coordinates":[-119.1382933,46.1838732000001,0]},{"type":"Point","coordinates":[-119.1947317,46.2249125000001,0]},{"type":"Point","coordinates":[-119.3800585,46.2166045000001,0]},{"type":"Point","coordinates":[-119.0342001,46.1649622,0]},{"type":"Point","coordinates":[-119.3028123,46.2002419,0]},{"type":"Point","coordinates":[-119.1564507,46.1842395,0]},{"type":"Point","coordinates":[-119.1189783,46.2021881000001,0]},{"type":"Point","coordinates":[-119.1206995,46.2022173,0]},{"type":"Point","coordinates":[-119.1192615,46.1992483000001,0]},{"type":"Point","coordinates":[-119.103672,46.1976079,0]},{"type":"Point","coordinates":[-119.1852491,46.1826389,0]},{"type":"Point","coordinates":[-119.1352061,46.1880789000001,0]},{"type":"Point","coordinates":[-119.1881113,46.2170054000001,0]},{"type":"Point","coordinates":[-119.2526652,46.2037008,0]},{"type":"Point","coordinates":[-119.0532732,46.143946,0]},{"type":"Point","coordinates":[-119.124192,46.2064288,0]},{"type":"Point","coordinates":[-119.196207,46.2245878000001,0]},{"type":"Point","coordinates":[-119.1548933,46.1830988,0]},{"type":"Point","coordinates":[-119.2013988,46.2171846000001,0]},{"type":"Point","coordinates":[-119.1190244,46.1885776,0]},{"type":"Point","coordinates":[-119.1866672,46.1892394000001,0]},{"type":"Point","coordinates":[-119.1264508,46.2063738000001,0]},{"type":"Point","coordinates":[-119.1242704,46.203737,0]},{"type":"Point","coordinates":[-119.1653841,46.1907114000001,0]},{"type":"Point","coordinates":[-119.0346338,46.1549214,0]},{"type":"Point","coordinates":[-119.1308405,46.2049143,0]},{"type":"Point","coordinates":[-119.1775181,46.2050345000001,0]},{"type":"Point","coordinates":[-119.1262556,46.1721238000001,0]},{"type":"Point","coordinates":[-119.169065,46.2182826000001,0]},{"type":"Point","coordinates":[-119.1310828,46.2076101000001,0]},{"type":"Point","coordinates":[-119.1549101,46.2064019000001,0]},{"type":"Point","coordinates":[-119.1317701,46.1975887,0]},{"type":"Point","coordinates":[-119.1501889,46.1775618,0]},{"type":"Point","coordinates":[-119.0372479,46.1551306000001,0]},{"type":"Point","coordinates":[-119.1900736,46.2082040000001,0]},{"type":"Point","coordinates":[-119.1948552,46.1792992000001,0]},{"type":"Point","coordinates":[-119.1986529,46.1670921,0]},{"type":"Point","coordinates":[-119.1966815,46.1673418,0]},{"type":"Point","coordinates":[-119.1499642,46.2054373,0]}]},"properties":{"UserName":"Michael Morgan","_count":42}}
]}
