{"name":"ID","type":"FeatureCollection"
,"features":[
{"type":"Feature","geometry":{"type":"Point","coordinates":[-116.1829574,43.5842014]},"properties":{"State":"ID","FCode":"74001","Feature":"Ambulance Services","OSM_ID":"1657672"}}
,{"type":"Feature","geometry":{"type":"Point","coordinates":[-114.9486057,42.9242632]},"properties":{"State":"ID","FCode":"74001","Feature":"Ambulance Services","OSM_ID":"1657894"}}
,{"type":"Feature","geometry":{"type":"Point","coordinates":[-111.8856777,42.7180496]},"properties":{"State":"ID","FCode":"74001","Feature":"Ambulance Services","OSM_ID":"1658205"}}
,{"type":"Feature","geometry":{"type":"Point","coordinates":[-112.8578816,42.7846893]},"properties":{"State":"ID","FCode":"74001","Feature":"Ambulance Services","OSM_ID":"1658458"}}
,{"type":"Feature","geometry":{"type":"Point","coordinates":[-111.3001568,42.3161423000001]},"properties":{"State":"ID","FCode":"74001","Feature":"Ambulance Services","OSM_ID":"1658585"}}
,{"type":"Feature","geometry":{"type":"Point","coordinates":[-111.7300279,42.5771671000001]},"properties":{"State":"ID","FCode":"74001","Feature":"Ambulance Services","OSM_ID":"1658623"}}
,{"type":"Feature","geometry":{"type":"Point","coordinates":[-115.9667408,43.9213834]},"properties":{"State":"ID","FCode":"74001","Feature":"Ambulance Services","OSM_ID":"1659055"}}
,{"type":"Feature","geometry":{"type":"Point","coordinates":[-116.5779683,48.1948507000001]},"properties":{"State":"ID","FCode":"74001","Feature":"Ambulance Services","OSM_ID":"1659178"}}
,{"type":"Feature","geometry":{"type":"Point","coordinates":[-111.6049538,42.6559471]},"properties":{"State":"ID","FCode":"74001","Feature":"Ambulance Services","OSM_ID":"1659358"}}
,{"type":"Feature","geometry":{"type":"Point","coordinates":[-112.4848436,43.8415671000001]},"properties":{"State":"ID","FCode":"74001","Feature":"Ambulance Services","OSM_ID":"1659450"}}
,{"type":"Feature","geometry":{"type":"Point","coordinates":[-112.8754829,42.5732243]},"properties":{"State":"ID","FCode":"74001","Feature":"Ambulance Services","OSM_ID":"1659477"}}
,{"type":"Feature","geometry":{"type":"Point","coordinates":[-113.6151437,43.9160830000001]},"properties":{"State":"ID","FCode":"74001","Feature":"Ambulance Services","OSM_ID":"1659613"}}
,{"type":"Feature","geometry":{"type":"Point","coordinates":[-111.6841471,43.9671416]},"properties":{"State":"ID","FCode":"74001","Feature":"Ambulance Services","OSM_ID":"1659747"}}
,{"type":"Feature","geometry":{"type":"Point","coordinates":[-115.2876111,44.1571364000001]},"properties":{"State":"ID","FCode":"74001","Feature":"Ambulance Services","OSM_ID":"1659780"}}
,{"type":"Feature","geometry":{"type":"Point","coordinates":[-115.8342789,43.8280434000001]},"properties":{"State":"ID","FCode":"74001","Feature":"Ambulance Services","OSM_ID":"1659887"}}
,{"type":"Feature","geometry":{"type":"Point","coordinates":[-112.2285585,44.1767688]},"properties":{"State":"ID","FCode":"74001","Feature":"Ambulance Services","OSM_ID":"1659947"}}
,{"type":"Feature","geometry":{"type":"Point","coordinates":[-116.8066044,43.5452712000001]},"properties":{"State":"ID","FCode":"74001","Feature":"Ambulance Services","OSM_ID":"1660150"}}
,{"type":"Feature","geometry":{"type":"Point","coordinates":[-112.2422493,42.1855525]},"properties":{"State":"ID","FCode":"74001","Feature":"Ambulance Services","OSM_ID":"1660153"}}
,{"type":"Feature","geometry":{"type":"Point","coordinates":[-115.0467362,43.3079541000001]},"properties":{"State":"ID","FCode":"82010","Feature":"Cemetery","OSM_ID":"1660237"}}
,{"type":"Feature","geometry":{"type":"Point","coordinates":[-111.9319198,44.3665797]},"properties":{"State":"ID","FCode":"82010","Feature":"Cemetery","OSM_ID":"1660403"}}
,{"type":"Feature","geometry":{"type":"Point","coordinates":[-115.2184732,47.0649204000001]},"properties":{"State":"ID","FCode":"82010","Feature":"Cemetery","OSM_ID":"1662583"}}
,{"type":"Feature","geometry":{"type":"Point","coordinates":[-111.0763315,43.6968647]},"properties":{"State":"ID","FCode":"82010","Feature":"Cemetery","OSM_ID":"1662910"}}
,{"type":"Feature","geometry":{"type":"Point","coordinates":[-111.740782,42.3585331]},"properties":{"State":"ID","FCode":"82010","Feature":"Cemetery","OSM_ID":"1663118"}}
,{"type":"Feature","geometry":{"type":"Point","coordinates":[-111.0910533,43.5932538000001]},"properties":{"State":"ID","FCode":"82010","Feature":"Cemetery","OSM_ID":"1663575"}}
,{"type":"Feature","geometry":{"type":"Point","coordinates":[-116.3948345,43.1726652]},"properties":{"State":"ID","FCode":"82010","Feature":"Cemetery","OSM_ID":"1663585"}}
,{"type":"Feature","geometry":{"type":"Point","coordinates":[-111.1427225,43.8154733000001]},"properties":{"State":"ID","FCode":"82010","Feature":"Cemetery","OSM_ID":"1664515"}}
,{"type":"Feature","geometry":{"type":"Point","coordinates":[-111.7116147,42.4374216000001]},"properties":{"State":"ID","FCode":"82010","Feature":"Cemetery","OSM_ID":"1664563"}}
,{"type":"Feature","geometry":{"type":"Point","coordinates":[-114.9439558,43.3857326]},"properties":{"State":"ID","FCode":"82010","Feature":"Cemetery","OSM_ID":"1665515"}}
,{"type":"Feature","geometry":{"type":"Point","coordinates":[-115.0712369,46.6685286000001]},"properties":{"State":"ID","FCode":"82010","Feature":"Cemetery","OSM_ID":"1665815"}}
,{"type":"Feature","geometry":{"type":"Point","coordinates":[-112.0157934,42.6013071]},"properties":{"State":"ID","FCode":"82010","Feature":"Cemetery","OSM_ID":"1666571"}}
,{"type":"Feature","geometry":{"type":"Point","coordinates":[-111.4188191,42.2652041000001]},"properties":{"State":"ID","FCode":"82010","Feature":"Cemetery","OSM_ID":"1667046"}}
,{"type":"Feature","geometry":{"type":"Point","coordinates":[-111.4413249,42.4835355000001]},"properties":{"State":"ID","FCode":"82010","Feature":"Cemetery","OSM_ID":"1669970"}}
,{"type":"Feature","geometry":{"type":"Point","coordinates":[-113.9372519,43.3282383000001]},"properties":{"State":"ID","FCode":"82010","Feature":"Cemetery","OSM_ID":"1670246"}}
,{"type":"Feature","geometry":{"type":"Point","coordinates":[-114.7472808,43.2674010000001]},"properties":{"State":"ID","FCode":"82010","Feature":"Cemetery","OSM_ID":"1671507"}}
,{"type":"Feature","geometry":{"type":"Point","coordinates":[-111.1943898,43.6579723]},"properties":{"State":"ID","FCode":"82010","Feature":"Cemetery","OSM_ID":"1671844"}}
,{"type":"Feature","geometry":{"type":"Point","coordinates":[-111.2213352,43.7079708000001]},"properties":{"State":"ID","FCode":"82010","Feature":"Cemetery","OSM_ID":"1672494"}}
,{"type":"Feature","geometry":{"type":"Point","coordinates":[-115.4990024,44.9560172000001]},"properties":{"State":"ID","FCode":"82010","Feature":"Cemetery","OSM_ID":"1673305"}}
,{"type":"Feature","geometry":{"type":"Point","coordinates":[-113.5966886,43.6712911000001]},"properties":{"State":"ID","FCode":"82010","Feature":"Cemetery","OSM_ID":"1673605"}}
,{"type":"Feature","geometry":{"type":"Point","coordinates":[-111.9046809,42.8540845000001]},"properties":{"State":"ID","FCode":"82010","Feature":"Cemetery","OSM_ID":"1674182"}}
,{"type":"Feature","geometry":{"type":"Point","coordinates":[-111.7755066,42.4451988000001]},"properties":{"State":"ID","FCode":"82010","Feature":"Cemetery","OSM_ID":"1674721"}}
,{"type":"Feature","geometry":{"type":"Point","coordinates":[-115.6870612,44.6643438]},"properties":{"State":"ID","FCode":"82010","Feature":"Cemetery","OSM_ID":"1674803"}}
,{"type":"Feature","geometry":{"type":"Point","coordinates":[-111.456044,42.3221476000001]},"properties":{"State":"ID","FCode":"82010","Feature":"Cemetery","OSM_ID":"1675950"}}
,{"type":"Feature","geometry":{"type":"Point","coordinates":[-115.8643317,47.6235387]},"properties":{"State":"ID","FCode":"82010","Feature":"Cemetery","OSM_ID":"1676247"}}
,{"type":"Feature","geometry":{"type":"Point","coordinates":[-112.2577465,42.5671384]},"properties":{"State":"ID","FCode":"82010","Feature":"Cemetery","OSM_ID":"1676985"}}
,{"type":"Feature","geometry":{"type":"Point","coordinates":[-115.7776101,43.9498949000001]},"properties":{"State":"ID","FCode":"82010","Feature":"Cemetery","OSM_ID":"1678059"}}
,{"type":"Feature","geometry":{"type":"Point","coordinates":[-111.3424532,44.6477008000001]},"properties":{"State":"ID","FCode":"82010","Feature":"Cemetery","OSM_ID":"1678667"}}
,{"type":"Feature","geometry":{"type":"Point","coordinates":[-111.9241415,44.3729687000001]},"properties":{"State":"ID","FCode":"82010","Feature":"Cemetery","OSM_ID":"1678801"}}
,{"type":"Feature","geometry":{"type":"Point","coordinates":[-116.4437546,44.7159986]},"properties":{"State":"ID","FCode":"82010","Feature":"Cemetery","OSM_ID":"1678832"}}
,{"type":"Feature","geometry":{"type":"Point","coordinates":[-112.8480548,43.9974044000001]},"properties":{"State":"ID","FCode":"82010","Feature":"Cemetery","OSM_ID":"1678834"}}
,{"type":"Feature","geometry":{"type":"Point","coordinates":[-114.304753,42.4590811]},"properties":{"State":"ID","FCode":"82010","Feature":"Cemetery","OSM_ID":"1679993"}}
,{"type":"Feature","geometry":{"type":"Point","coordinates":[-111.281058,43.4454727]},"properties":{"State":"ID","FCode":"82010","Feature":"Cemetery","OSM_ID":"1681323"}}
,{"type":"Feature","geometry":{"type":"Point","coordinates":[-114.1783601,42.4057471]},"properties":{"State":"ID","FCode":"82010","Feature":"Cemetery","OSM_ID":"1683720"}}
,{"type":"Feature","geometry":{"type":"Point","coordinates":[-111.0821652,43.7240866000001]},"properties":{"State":"ID","FCode":"82010","Feature":"Cemetery","OSM_ID":"1683788"}}
,{"type":"Feature","geometry":{"type":"Point","coordinates":[-111.0899177,42.3613188]},"properties":{"State":"ID","FCode":"82010","Feature":"Cemetery","OSM_ID":"1684159"}}
,{"type":"Feature","geometry":{"type":"Point","coordinates":[-112.9011135,44.1385176000001]},"properties":{"State":"ID","FCode":"82010","Feature":"Cemetery","OSM_ID":"1685500"}}
,{"type":"Feature","geometry":{"type":"Point","coordinates":[-113.7769617,42.6365756000001]},"properties":{"State":"ID","FCode":"82010","Feature":"Cemetery","OSM_ID":"1686586"}}
,{"type":"Feature","geometry":{"type":"Point","coordinates":[-111.0540808,42.2852088000001]},"properties":{"State":"ID","FCode":"82010","Feature":"Cemetery","OSM_ID":"1686797"}}
,{"type":"Feature","geometry":{"type":"Point","coordinates":[-116.6854371,44.4718296]},"properties":{"State":"ID","FCode":"82010","Feature":"Cemetery","OSM_ID":"1687134"}}
,{"type":"Feature","geometry":{"type":"Point","coordinates":[-111.2565903,42.2060408]},"properties":{"State":"ID","FCode":"82010","Feature":"Cemetery","OSM_ID":"1687436"}}
,{"type":"Feature","geometry":{"type":"Point","coordinates":[-111.2049465,43.8624154]},"properties":{"State":"ID","FCode":"82010","Feature":"Cemetery","OSM_ID":"1687561"}}
,{"type":"Feature","geometry":{"type":"Point","coordinates":[-111.7299503,42.5496427]},"properties":{"State":"ID","FCode":"82010","Feature":"Cemetery","OSM_ID":"1692142"}}
,{"type":"Feature","geometry":{"type":"Point","coordinates":[-115.9765169,44.4262833000001]},"properties":{"State":"ID","FCode":"82010","Feature":"Cemetery","OSM_ID":"1692707"}}
,{"type":"Feature","geometry":{"type":"Point","coordinates":[-111.4040968,42.2921486000001]},"properties":{"State":"ID","FCode":"82010","Feature":"Cemetery","OSM_ID":"1692915"}}
,{"type":"Feature","geometry":{"type":"Point","coordinates":[-111.4335459,42.4479804000001]},"properties":{"State":"ID","FCode":"82010","Feature":"Cemetery","OSM_ID":"1693977"}}
,{"type":"Feature","geometry":{"type":"Point","coordinates":[-115.8423319,43.8326713000001]},"properties":{"State":"ID","FCode":"82010","Feature":"Cemetery","OSM_ID":"1694195"}}
,{"type":"Feature","geometry":{"type":"Point","coordinates":[-113.6440964,42.3379478000001]},"properties":{"State":"ID","FCode":"82010","Feature":"Cemetery","OSM_ID":"1694440"}}
,{"type":"Feature","geometry":{"type":"Point","coordinates":[-111.205224,43.8282487000001]},"properties":{"State":"ID","FCode":"82010","Feature":"Cemetery","OSM_ID":"1695119"}}
,{"type":"Feature","geometry":{"type":"Point","coordinates":[-115.8426097,43.8326713000001]},"properties":{"State":"ID","FCode":"82010","Feature":"Cemetery","OSM_ID":"1695889"}}
,{"type":"Feature","geometry":{"type":"Point","coordinates":[-114.7903399,43.4129565000001]},"properties":{"State":"ID","FCode":"82010","Feature":"Cemetery","OSM_ID":"1696339"}}
,{"type":"Feature","geometry":{"type":"Point","coordinates":[-111.2818846,42.9363097]},"properties":{"State":"ID","FCode":"82010","Feature":"Cemetery","OSM_ID":"1696656"}}
,{"type":"Feature","geometry":{"type":"Point","coordinates":[-111.7820914,43.8252913000001]},"properties":{"State":"ID","FCode":"73006","Feature":"College / University","OSM_ID":"1697472"}}
,{"type":"Feature","geometry":{"type":"Point","coordinates":[-111.9846452,43.4817998]},"properties":{"State":"ID","FCode":"73006","Feature":"College / University","OSM_ID":"1697739"}}
,{"type":"Feature","geometry":{"type":"Point","coordinates":[-111.7847282,43.8153838000001]},"properties":{"State":"ID","FCode":"73006","Feature":"College / University","OSM_ID":"1697918"}}
,{"type":"Feature","geometry":{"type":"Point","coordinates":[-111.3331389,44.6286642000001]},"properties":{"State":"ID","FCode":"74026","Feature":"Fire Station / EMS Station","OSM_ID":"1698933"}}
,{"type":"Feature","geometry":{"type":"Point","coordinates":[-116.874168,44.3540591]},"properties":{"State":"ID","FCode":"74026","Feature":"Fire Station / EMS Station","OSM_ID":"1699216"}}
,{"type":"Feature","geometry":{"type":"Point","coordinates":[-114.4811197,42.4839753000001]},"properties":{"State":"ID","FCode":"74026","Feature":"Fire Station / EMS Station","OSM_ID":"1699302"}}
,{"type":"Feature","geometry":{"type":"Point","coordinates":[-112.3454769,43.1917297000001]},"properties":{"State":"ID","FCode":"74026","Feature":"Fire Station / EMS Station","OSM_ID":"1699351"}}
,{"type":"Feature","geometry":{"type":"Point","coordinates":[-115.8903469,46.2504294]},"properties":{"State":"ID","FCode":"74026","Feature":"Fire Station / EMS Station","OSM_ID":"1699406"}}
,{"type":"Feature","geometry":{"type":"Point","coordinates":[-112.190528,42.6487822]},"properties":{"State":"ID","FCode":"74026","Feature":"Fire Station / EMS Station","OSM_ID":"1700019"}}
,{"type":"Feature","geometry":{"type":"Point","coordinates":[-116.0771271,46.3261335]},"properties":{"State":"ID","FCode":"74026","Feature":"Fire Station / EMS Station","OSM_ID":"1700207"}}
,{"type":"Feature","geometry":{"type":"Point","coordinates":[-111.4373474,42.4572397000001]},"properties":{"State":"ID","FCode":"74026","Feature":"Fire Station / EMS Station","OSM_ID":"1700426"}}
,{"type":"Feature","geometry":{"type":"Point","coordinates":[-111.4384929,44.4658870000001]},"properties":{"State":"ID","FCode":"74026","Feature":"Fire Station / EMS Station","OSM_ID":"1700862"}}
,{"type":"Feature","geometry":{"type":"Point","coordinates":[-113.3665311,43.7333340000001]},"properties":{"State":"ID","FCode":"74026","Feature":"Fire Station / EMS Station","OSM_ID":"1701112"}}
,{"type":"Feature","geometry":{"type":"Point","coordinates":[-112.1824695,43.3061812]},"properties":{"State":"ID","FCode":"74026","Feature":"Fire Station / EMS Station","OSM_ID":"1701279"}}
,{"type":"Feature","geometry":{"type":"Point","coordinates":[-111.097774,43.7440096]},"properties":{"State":"ID","FCode":"74026","Feature":"Fire Station / EMS Station","OSM_ID":"1701636"}}
,{"type":"Feature","geometry":{"type":"Point","coordinates":[-115.8385749,43.8234955]},"properties":{"State":"ID","FCode":"74026","Feature":"Fire Station / EMS Station","OSM_ID":"1701726"}}
,{"type":"Feature","geometry":{"type":"Point","coordinates":[-116.3838729,45.3196356]},"properties":{"State":"ID","FCode":"74026","Feature":"Fire Station / EMS Station","OSM_ID":"1701892"}}
,{"type":"Feature","geometry":{"type":"Point","coordinates":[-116.0474239,46.5187952000001]},"properties":{"State":"ID","FCode":"74026","Feature":"Fire Station / EMS Station","OSM_ID":"1701964"}}
,{"type":"Feature","geometry":{"type":"Point","coordinates":[-111.334731,44.4968535]},"properties":{"State":"ID","FCode":"74026","Feature":"Fire Station / EMS Station","OSM_ID":"1702118"}}
,{"type":"Feature","geometry":{"type":"Point","coordinates":[-112.0121051,43.6960373000001]},"properties":{"State":"ID","FCode":"74026","Feature":"Fire Station / EMS Station","OSM_ID":"1702123"}}
,{"type":"Feature","geometry":{"type":"Point","coordinates":[-112.6558738,43.5929827000001]},"properties":{"State":"ID","FCode":"74026","Feature":"Fire Station / EMS Station","OSM_ID":"1702323"}}
,{"type":"Feature","geometry":{"type":"Point","coordinates":[-112.204588,43.9251343]},"properties":{"State":"ID","FCode":"74026","Feature":"Fire Station / EMS Station","OSM_ID":"1702444"}}
,{"type":"Feature","geometry":{"type":"Point","coordinates":[-112.0047811,43.4692055]},"properties":{"State":"ID","FCode":"74026","Feature":"Fire Station / EMS Station","OSM_ID":"1702600"}}
,{"type":"Feature","geometry":{"type":"Point","coordinates":[-116.8499172,48.0501093]},"properties":{"State":"ID","FCode":"74026","Feature":"Fire Station / EMS Station","OSM_ID":"1702605"}}
,{"type":"Feature","geometry":{"type":"Point","coordinates":[-114.5964724,42.2182955000001]},"properties":{"State":"ID","FCode":"74026","Feature":"Fire Station / EMS Station","OSM_ID":"1702844"}}
,{"type":"Feature","geometry":{"type":"Point","coordinates":[-111.3965859,42.0351481000001]},"properties":{"State":"ID","FCode":"74026","Feature":"Fire Station / EMS Station","OSM_ID":"1702944"}}
,{"type":"Feature","geometry":{"type":"Point","coordinates":[-111.4453753,44.0741996]},"properties":{"State":"ID","FCode":"74026","Feature":"Fire Station / EMS Station","OSM_ID":"1702969"}}
,{"type":"Feature","geometry":{"type":"Point","coordinates":[-111.9594485,43.5966931]},"properties":{"State":"ID","FCode":"74026","Feature":"Fire Station / EMS Station","OSM_ID":"1703253"}}
,{"type":"Feature","geometry":{"type":"Point","coordinates":[-111.2540799,42.048959]},"properties":{"State":"ID","FCode":"74026","Feature":"Fire Station / EMS Station","OSM_ID":"1703412"}}
,{"type":"Feature","geometry":{"type":"Point","coordinates":[-113.357341,44.6794727000001]},"properties":{"State":"ID","FCode":"74026","Feature":"Fire Station / EMS Station","OSM_ID":"1703523"}}
,{"type":"Feature","geometry":{"type":"Point","coordinates":[-115.9859294,43.6756212000001]},"properties":{"State":"ID","FCode":"74026","Feature":"Fire Station / EMS Station","OSM_ID":"1703636"}}
,{"type":"Feature","geometry":{"type":"Point","coordinates":[-116.8067212,47.6764380000001]},"properties":{"State":"ID","FCode":"74026","Feature":"Fire Station / EMS Station","OSM_ID":"1703915"}}
,{"type":"Feature","geometry":{"type":"Point","coordinates":[-111.8782567,42.0938163000001]},"properties":{"State":"ID","FCode":"74026","Feature":"Fire Station / EMS Station","OSM_ID":"1704617"}}
,{"type":"Feature","geometry":{"type":"Point","coordinates":[-111.9995747,43.51165]},"properties":{"State":"ID","FCode":"74026","Feature":"Fire Station / EMS Station","OSM_ID":"1704620"}}
,{"type":"Feature","geometry":{"type":"Point","coordinates":[-112.8578697,42.7846893]},"properties":{"State":"ID","FCode":"74026","Feature":"Fire Station / EMS Station","OSM_ID":"1704680"}}
,{"type":"Feature","geometry":{"type":"Point","coordinates":[-112.9492204,43.5262328000001]},"properties":{"State":"ID","FCode":"74026","Feature":"Fire Station / EMS Station","OSM_ID":"1704903"}}
,{"type":"Feature","geometry":{"type":"Point","coordinates":[-112.0383501,43.4942981]},"properties":{"State":"ID","FCode":"74026","Feature":"Fire Station / EMS Station","OSM_ID":"1704923"}}
,{"type":"Feature","geometry":{"type":"Point","coordinates":[-112.5348682,43.1889839]},"properties":{"State":"ID","FCode":"74026","Feature":"Fire Station / EMS Station","OSM_ID":"1705193"}}
,{"type":"Feature","geometry":{"type":"Point","coordinates":[-111.3692478,42.4766912000001]},"properties":{"State":"ID","FCode":"74026","Feature":"Fire Station / EMS Station","OSM_ID":"1705195"}}
,{"type":"Feature","geometry":{"type":"Point","coordinates":[-116.4377587,44.728938]},"properties":{"State":"ID","FCode":"74026","Feature":"Fire Station / EMS Station","OSM_ID":"1705224"}}
,{"type":"Feature","geometry":{"type":"Point","coordinates":[-111.6833932,43.9652588000001]},"properties":{"State":"ID","FCode":"74026","Feature":"Fire Station / EMS Station","OSM_ID":"1705258"}}
,{"type":"Feature","geometry":{"type":"Point","coordinates":[-111.3964643,42.2882302]},"properties":{"State":"ID","FCode":"74026","Feature":"Fire Station / EMS Station","OSM_ID":"1705262"}}
,{"type":"Feature","geometry":{"type":"Point","coordinates":[-116.309123,45.5373642000001]},"properties":{"State":"ID","FCode":"74026","Feature":"Fire Station / EMS Station","OSM_ID":"1705328"}}
,{"type":"Feature","geometry":{"type":"Point","coordinates":[-114.8687625,42.5194797]},"properties":{"State":"ID","FCode":"74026","Feature":"Fire Station / EMS Station","OSM_ID":"1705393"}}
,{"type":"Feature","geometry":{"type":"Point","coordinates":[-111.9935604,42.1238977]},"properties":{"State":"ID","FCode":"74026","Feature":"Fire Station / EMS Station","OSM_ID":"1705400"}}
,{"type":"Feature","geometry":{"type":"Point","coordinates":[-111.3200013,42.3913867000001]},"properties":{"State":"ID","FCode":"74026","Feature":"Fire Station / EMS Station","OSM_ID":"1705582"}}
,{"type":"Feature","geometry":{"type":"Point","coordinates":[-111.1095279,43.5992258000001]},"properties":{"State":"ID","FCode":"74026","Feature":"Fire Station / EMS Station","OSM_ID":"1705584"}}
,{"type":"Feature","geometry":{"type":"Point","coordinates":[-116.9666973,47.7850739]},"properties":{"State":"ID","FCode":"74026","Feature":"Fire Station / EMS Station","OSM_ID":"1705632"}}
,{"type":"Feature","geometry":{"type":"Point","coordinates":[-111.7848283,43.7146188]},"properties":{"State":"ID","FCode":"74026","Feature":"Fire Station / EMS Station","OSM_ID":"1705783"}}
,{"type":"Feature","geometry":{"type":"Point","coordinates":[-112.0825397,43.4820814]},"properties":{"State":"ID","FCode":"74026","Feature":"Fire Station / EMS Station","OSM_ID":"1705930"}}
,{"type":"Feature","geometry":{"type":"Point","coordinates":[-116.2251061,43.5613878]},"properties":{"State":"ID","FCode":"74026","Feature":"Fire Station / EMS Station","OSM_ID":"1706321"}}
,{"type":"Feature","geometry":{"type":"Point","coordinates":[-114.7929075,43.3457877000001]},"properties":{"State":"ID","FCode":"74026","Feature":"Fire Station / EMS Station","OSM_ID":"1707026"}}
,{"type":"Feature","geometry":{"type":"Point","coordinates":[-112.2286013,44.1765197]},"properties":{"State":"ID","FCode":"74026","Feature":"Fire Station / EMS Station","OSM_ID":"1707106"}}
,{"type":"Feature","geometry":{"type":"Point","coordinates":[-111.0649446,42.3575331000001]},"properties":{"State":"ID","FCode":"74026","Feature":"Fire Station / EMS Station","OSM_ID":"1707186"}}
,{"type":"Feature","geometry":{"type":"Point","coordinates":[-115.6219527,44.0797499000001]},"properties":{"State":"ID","FCode":"74026","Feature":"Fire Station / EMS Station","OSM_ID":"1707375"}}
,{"type":"Feature","geometry":{"type":"Point","coordinates":[-112.4825563,43.8410153]},"properties":{"State":"ID","FCode":"74026","Feature":"Fire Station / EMS Station","OSM_ID":"1707715"}}
,{"type":"Feature","geometry":{"type":"Point","coordinates":[-111.306411,42.3223977000001]},"properties":{"State":"ID","FCode":"74026","Feature":"Fire Station / EMS Station","OSM_ID":"1707789"}}
,{"type":"Feature","geometry":{"type":"Point","coordinates":[-116.29846,48.2427324000001]},"properties":{"State":"ID","FCode":"74026","Feature":"Fire Station / EMS Station","OSM_ID":"1707872"}}
,{"type":"Feature","geometry":{"type":"Point","coordinates":[-112.6831162,43.0809935]},"properties":{"State":"ID","FCode":"74026","Feature":"Fire Station / EMS Station","OSM_ID":"1707911"}}
,{"type":"Feature","geometry":{"type":"Point","coordinates":[-111.3891792,42.1119814]},"properties":{"State":"ID","FCode":"74026","Feature":"Fire Station / EMS Station","OSM_ID":"1708101"}}
,{"type":"Feature","geometry":{"type":"Point","coordinates":[-111.7300279,42.5771671000001]},"properties":{"State":"ID","FCode":"74026","Feature":"Fire Station / EMS Station","OSM_ID":"1708395"}}
,{"type":"Feature","geometry":{"type":"Point","coordinates":[-116.0030712,43.7457858000001]},"properties":{"State":"ID","FCode":"74026","Feature":"Fire Station / EMS Station","OSM_ID":"1708430"}}
,{"type":"Feature","geometry":{"type":"Point","coordinates":[-114.8498743,42.6707564000001]},"properties":{"State":"ID","FCode":"74026","Feature":"Fire Station / EMS Station","OSM_ID":"1708447"}}
,{"type":"Feature","geometry":{"type":"Point","coordinates":[-111.9638739,43.4776076000001]},"properties":{"State":"ID","FCode":"74026","Feature":"Fire Station / EMS Station","OSM_ID":"1708572"}}
,{"type":"Feature","geometry":{"type":"Point","coordinates":[-116.7805302,48.1475669000001]},"properties":{"State":"ID","FCode":"74026","Feature":"Fire Station / EMS Station","OSM_ID":"1708636"}}
,{"type":"Feature","geometry":{"type":"Point","coordinates":[-111.2966589,42.3354629]},"properties":{"State":"ID","FCode":"74026","Feature":"Fire Station / EMS Station","OSM_ID":"1708648"}}
,{"type":"Feature","geometry":{"type":"Point","coordinates":[-112.0641445,43.5155433]},"properties":{"State":"ID","FCode":"74026","Feature":"Fire Station / EMS Station","OSM_ID":"1708677"}}
,{"type":"Feature","geometry":{"type":"Point","coordinates":[-111.3383759,43.4537357]},"properties":{"State":"ID","FCode":"74026","Feature":"Fire Station / EMS Station","OSM_ID":"1708809"}}
,{"type":"Feature","geometry":{"type":"Point","coordinates":[-116.1829573,43.5842010000001]},"properties":{"State":"ID","FCode":"74026","Feature":"Fire Station / EMS Station","OSM_ID":"1709331"}}
,{"type":"Feature","geometry":{"type":"Point","coordinates":[-116.5779552,48.1948652]},"properties":{"State":"ID","FCode":"74026","Feature":"Fire Station / EMS Station","OSM_ID":"1709352"}}
,{"type":"Feature","geometry":{"type":"Point","coordinates":[-116.4343839,44.5568485000001]},"properties":{"State":"ID","FCode":"74026","Feature":"Fire Station / EMS Station","OSM_ID":"1709596"}}
,{"type":"Feature","geometry":{"type":"Point","coordinates":[-115.5979476,44.0761183000001]},"properties":{"State":"ID","FCode":"74026","Feature":"Fire Station / EMS Station","OSM_ID":"1709942"}}
,{"type":"Feature","geometry":{"type":"Point","coordinates":[-112.1254351,43.3809927]},"properties":{"State":"ID","FCode":"74026","Feature":"Fire Station / EMS Station","OSM_ID":"1710043"}}
,{"type":"Feature","geometry":{"type":"Point","coordinates":[-115.9206161,43.7503131]},"properties":{"State":"ID","FCode":"74026","Feature":"Fire Station / EMS Station","OSM_ID":"1710050"}}
,{"type":"Feature","geometry":{"type":"Point","coordinates":[-112.2455783,42.1863042000001]},"properties":{"State":"ID","FCode":"74026","Feature":"Fire Station / EMS Station","OSM_ID":"1710075"}}
,{"type":"Feature","geometry":{"type":"Point","coordinates":[-116.7312387,43.018355]},"properties":{"State":"ID","FCode":"74026","Feature":"Fire Station / EMS Station","OSM_ID":"1710097"}}
,{"type":"Feature","geometry":{"type":"Point","coordinates":[-111.4001848,44.3736922000001]},"properties":{"State":"ID","FCode":"74026","Feature":"Fire Station / EMS Station","OSM_ID":"1710147"}}
,{"type":"Feature","geometry":{"type":"Point","coordinates":[-111.8831719,42.7194566000001]},"properties":{"State":"ID","FCode":"74026","Feature":"Fire Station / EMS Station","OSM_ID":"1710339"}}
,{"type":"Feature","geometry":{"type":"Point","coordinates":[-113.1607155,42.3254829000001]},"properties":{"State":"ID","FCode":"74026","Feature":"Fire Station / EMS Station","OSM_ID":"1710390"}}
,{"type":"Feature","geometry":{"type":"Point","coordinates":[-112.1248786,42.4284302]},"properties":{"State":"ID","FCode":"74026","Feature":"Fire Station / EMS Station","OSM_ID":"1710473"}}
,{"type":"Feature","geometry":{"type":"Point","coordinates":[-115.4430086,45.8272186]},"properties":{"State":"ID","FCode":"74026","Feature":"Fire Station / EMS Station","OSM_ID":"1710556"}}
,{"type":"Feature","geometry":{"type":"Point","coordinates":[-111.1286619,42.1412145]},"properties":{"State":"ID","FCode":"74026","Feature":"Fire Station / EMS Station","OSM_ID":"1711367"}}
,{"type":"Feature","geometry":{"type":"Point","coordinates":[-112.5365273,43.9691397]},"properties":{"State":"ID","FCode":"74026","Feature":"Fire Station / EMS Station","OSM_ID":"1711491"}}
,{"type":"Feature","geometry":{"type":"Point","coordinates":[-116.2154584,43.5659536000001]},"properties":{"State":"ID","FCode":"74026","Feature":"Fire Station / EMS Station","OSM_ID":"1711631"}}
,{"type":"Feature","geometry":{"type":"Point","coordinates":[-115.3068746,44.1411807000001]},"properties":{"State":"ID","FCode":"74026","Feature":"Fire Station / EMS Station","OSM_ID":"1711878"}}
,{"type":"Feature","geometry":{"type":"Point","coordinates":[-112.0226913,42.6188288000001]},"properties":{"State":"ID","FCode":"74026","Feature":"Fire Station / EMS Station","OSM_ID":"1711967"}}
,{"type":"Feature","geometry":{"type":"Point","coordinates":[-111.7834876,43.8268877]},"properties":{"State":"ID","FCode":"74026","Feature":"Fire Station / EMS Station","OSM_ID":"1712100"}}
,{"type":"Feature","geometry":{"type":"Point","coordinates":[-111.6029508,42.6566386000001]},"properties":{"State":"ID","FCode":"74026","Feature":"Fire Station / EMS Station","OSM_ID":"1712637"}}
,{"type":"Feature","geometry":{"type":"Point","coordinates":[-116.5738158,44.6328940000001]},"properties":{"State":"ID","FCode":"74026","Feature":"Fire Station / EMS Station","OSM_ID":"1713210"}}
,{"type":"Feature","geometry":{"type":"Point","coordinates":[-116.7334928,44.4714883]},"properties":{"State":"ID","FCode":"74026","Feature":"Fire Station / EMS Station","OSM_ID":"1713237"}}
,{"type":"Feature","geometry":{"type":"Point","coordinates":[-113.2940546,42.5166785000001]},"properties":{"State":"ID","FCode":"74026","Feature":"Fire Station / EMS Station","OSM_ID":"1713267"}}
,{"type":"Feature","geometry":{"type":"Point","coordinates":[-112.1711856,42.5606422000001]},"properties":{"State":"ID","FCode":"74026","Feature":"Fire Station / EMS Station","OSM_ID":"1713351"}}
,{"type":"Feature","geometry":{"type":"Point","coordinates":[-115.1261908,43.8026935]},"properties":{"State":"ID","FCode":"74026","Feature":"Fire Station / EMS Station","OSM_ID":"1713537"}}
,{"type":"Feature","geometry":{"type":"Point","coordinates":[-115.4931073,44.9610498000001]},"properties":{"State":"ID","FCode":"74026","Feature":"Fire Station / EMS Station","OSM_ID":"1713740"}}
,{"type":"Feature","geometry":{"type":"Point","coordinates":[-111.1642725,43.8137459000001]},"properties":{"State":"ID","FCode":"74026","Feature":"Fire Station / EMS Station","OSM_ID":"1713753"}}
,{"type":"Feature","geometry":{"type":"Point","coordinates":[-111.4006134,42.2259752000001]},"properties":{"State":"ID","FCode":"74026","Feature":"Fire Station / EMS Station","OSM_ID":"1713948"}}
,{"type":"Feature","geometry":{"type":"Point","coordinates":[-116.5509655,48.0653483]},"properties":{"State":"ID","FCode":"74026","Feature":"Fire Station / EMS Station","OSM_ID":"1713953"}}
,{"type":"Feature","geometry":{"type":"Point","coordinates":[-111.2671686,42.2186620000001]},"properties":{"State":"ID","FCode":"74026","Feature":"Fire Station / EMS Station","OSM_ID":"1714324"}}
,{"type":"Feature","geometry":{"type":"Point","coordinates":[-113.9433311,43.3189668000001]},"properties":{"State":"ID","FCode":"74026","Feature":"Fire Station / EMS Station","OSM_ID":"1714533"}}
,{"type":"Feature","geometry":{"type":"Point","coordinates":[-116.3764876,45.3677489]},"properties":{"State":"ID","FCode":"74026","Feature":"Fire Station / EMS Station","OSM_ID":"1714824"}}
,{"type":"Feature","geometry":{"type":"Point","coordinates":[-111.7733606,43.6308249000001]},"properties":{"State":"ID","FCode":"74026","Feature":"Fire Station / EMS Station","OSM_ID":"1715146"}}
,{"type":"Feature","geometry":{"type":"Point","coordinates":[-115.9949882,44.4037922000001]},"properties":{"State":"ID","FCode":"74026","Feature":"Fire Station / EMS Station","OSM_ID":"1715518"}}
,{"type":"Feature","geometry":{"type":"Point","coordinates":[-115.920733,43.7501388000001]},"properties":{"State":"ID","FCode":"74026","Feature":"Fire Station / EMS Station","OSM_ID":"1715635"}}
,{"type":"Feature","geometry":{"type":"Point","coordinates":[-115.4167806,44.1180363]},"properties":{"State":"ID","FCode":"74026","Feature":"Fire Station / EMS Station","OSM_ID":"1715641"}}
,{"type":"Feature","geometry":{"type":"Point","coordinates":[-116.6758389,44.5719755000001]},"properties":{"State":"ID","FCode":"74026","Feature":"Fire Station / EMS Station","OSM_ID":"1715766"}}
,{"type":"Feature","geometry":{"type":"Point","coordinates":[-116.866877,47.9647834]},"properties":{"State":"ID","FCode":"74026","Feature":"Fire Station / EMS Station","OSM_ID":"1716176"}}
,{"type":"Feature","geometry":{"type":"Point","coordinates":[-112.8754834,42.5732315000001]},"properties":{"State":"ID","FCode":"74026","Feature":"Fire Station / EMS Station","OSM_ID":"1716270"}}
,{"type":"Feature","geometry":{"type":"Point","coordinates":[-112.1270862,43.7184001000001]},"properties":{"State":"ID","FCode":"74026","Feature":"Fire Station / EMS Station","OSM_ID":"1716341"}}
,{"type":"Feature","geometry":{"type":"Point","coordinates":[-111.5895087,42.6549483000001]},"properties":{"State":"ID","FCode":"74026","Feature":"Fire Station / EMS Station","OSM_ID":"1716342"}}
,{"type":"Feature","geometry":{"type":"Point","coordinates":[-111.9146516,43.6840901]},"properties":{"State":"ID","FCode":"74026","Feature":"Fire Station / EMS Station","OSM_ID":"1716380"}}
,{"type":"Feature","geometry":{"type":"Point","coordinates":[-112.8578518,42.7846936]},"properties":{"State":"ID","FCode":"74026","Feature":"Fire Station / EMS Station","OSM_ID":"1716404"}}
,{"type":"Feature","geometry":{"type":"Point","coordinates":[-115.981267,47.6396647]},"properties":{"State":"ID","FCode":"74026","Feature":"Fire Station / EMS Station","OSM_ID":"1716442"}}
,{"type":"Feature","geometry":{"type":"Point","coordinates":[-115.8563549,47.6270482]},"properties":{"State":"ID","FCode":"74026","Feature":"Fire Station / EMS Station","OSM_ID":"1716520"}}
,{"type":"Feature","geometry":{"type":"Point","coordinates":[-111.9959683,43.7211526]},"properties":{"State":"ID","FCode":"74026","Feature":"Fire Station / EMS Station","OSM_ID":"1716598"}}
,{"type":"Feature","geometry":{"type":"Point","coordinates":[-112.7065625,43.8460536000001]},"properties":{"State":"ID","FCode":"74026","Feature":"Fire Station / EMS Station","OSM_ID":"1717037"}}
,{"type":"Feature","geometry":{"type":"Point","coordinates":[-116.0893398,44.4954632000001]},"properties":{"State":"ID","FCode":"74026","Feature":"Fire Station / EMS Station","OSM_ID":"1717082"}}
,{"type":"Feature","geometry":{"type":"Point","coordinates":[-116.4480947,44.6348891000001]},"properties":{"State":"ID","FCode":"74026","Feature":"Fire Station / EMS Station","OSM_ID":"1717099"}}
,{"type":"Feature","geometry":{"type":"Point","coordinates":[-112.2466087,42.1869042000001]},"properties":{"State":"ID","FCode":"74026","Feature":"Fire Station / EMS Station","OSM_ID":"1717137"}}
,{"type":"Feature","geometry":{"type":"Point","coordinates":[-116.3103553,45.7419503]},"properties":{"State":"ID","FCode":"74026","Feature":"Fire Station / EMS Station","OSM_ID":"1717153"}}
,{"type":"Feature","geometry":{"type":"Point","coordinates":[-116.4384108,44.7286287000001]},"properties":{"State":"ID","FCode":"74034","Feature":"Law Enforcement","OSM_ID":"1717644"}}
,{"type":"Feature","geometry":{"type":"Point","coordinates":[-111.7828701,43.8264213000001]},"properties":{"State":"ID","FCode":"74034","Feature":"Law Enforcement","OSM_ID":"1717953"}}
,{"type":"Feature","geometry":{"type":"Point","coordinates":[-116.5580803,48.3082175000001]},"properties":{"State":"ID","FCode":"74034","Feature":"Law Enforcement","OSM_ID":"1718178"}}
,{"type":"Feature","geometry":{"type":"Point","coordinates":[-112.1254126,43.3810997000001]},"properties":{"State":"ID","FCode":"74034","Feature":"Law Enforcement","OSM_ID":"1718422"}}
,{"type":"Feature","geometry":{"type":"Point","coordinates":[-115.8331789,43.8282075000001]},"properties":{"State":"ID","FCode":"74034","Feature":"Law Enforcement","OSM_ID":"1718845"}}
,{"type":"Feature","geometry":{"type":"Point","coordinates":[-113.3026168,43.6353328000001]},"properties":{"State":"ID","FCode":"74034","Feature":"Law Enforcement","OSM_ID":"1718955"}}
,{"type":"Feature","geometry":{"type":"Point","coordinates":[-111.878544,42.096554]},"properties":{"State":"ID","FCode":"74034","Feature":"Law Enforcement","OSM_ID":"1719006"}}
,{"type":"Feature","geometry":{"type":"Point","coordinates":[-115.8395274,43.8229834000001]},"properties":{"State":"ID","FCode":"74034","Feature":"Law Enforcement","OSM_ID":"1719211"}}
,{"type":"Feature","geometry":{"type":"Point","coordinates":[-111.5896386,42.6552713]},"properties":{"State":"ID","FCode":"74034","Feature":"Law Enforcement","OSM_ID":"1719259"}}
,{"type":"Feature","geometry":{"type":"Point","coordinates":[-116.5507768,43.2157292000001]},"properties":{"State":"ID","FCode":"74034","Feature":"Law Enforcement","OSM_ID":"1719286"}}
,{"type":"Feature","geometry":{"type":"Point","coordinates":[-112.2329491,44.1765501]},"properties":{"State":"ID","FCode":"74034","Feature":"Law Enforcement","OSM_ID":"1719593"}}
,{"type":"Feature","geometry":{"type":"Point","coordinates":[-116.4353228,44.7380224]},"properties":{"State":"ID","FCode":"74034","Feature":"Law Enforcement","OSM_ID":"1719923"}}
,{"type":"Feature","geometry":{"type":"Point","coordinates":[-114.7935387,43.3459429000001]},"properties":{"State":"ID","FCode":"74034","Feature":"Law Enforcement","OSM_ID":"1720267"}}
,{"type":"Feature","geometry":{"type":"Point","coordinates":[-111.8781257,42.0959064]},"properties":{"State":"ID","FCode":"74034","Feature":"Law Enforcement","OSM_ID":"1720536"}}
,{"type":"Feature","geometry":{"type":"Point","coordinates":[-112.3445311,43.1942518000001]},"properties":{"State":"ID","FCode":"74034","Feature":"Law Enforcement","OSM_ID":"1720679"}}
,{"type":"Feature","geometry":{"type":"Point","coordinates":[-111.6817831,43.9706937]},"properties":{"State":"ID","FCode":"74034","Feature":"Law Enforcement","OSM_ID":"1720681"}}
,{"type":"Feature","geometry":{"type":"Point","coordinates":[-112.2454593,42.1864802000001]},"properties":{"State":"ID","FCode":"74034","Feature":"Law Enforcement","OSM_ID":"1720919"}}
,{"type":"Feature","geometry":{"type":"Point","coordinates":[-111.6848616,43.9680277000001]},"properties":{"State":"ID","FCode":"74034","Feature":"Law Enforcement","OSM_ID":"1720970"}}
,{"type":"Feature","geometry":{"type":"Point","coordinates":[-116.8693165,47.9654011000001]},"properties":{"State":"ID","FCode":"74034","Feature":"Law Enforcement","OSM_ID":"1721420"}}
,{"type":"Feature","geometry":{"type":"Point","coordinates":[-111.911522,43.6729689000001]},"properties":{"State":"ID","FCode":"74034","Feature":"Law Enforcement","OSM_ID":"1721721"}}
,{"type":"Feature","geometry":{"type":"Point","coordinates":[-111.4006458,42.227857]},"properties":{"State":"ID","FCode":"74034","Feature":"Law Enforcement","OSM_ID":"1721899"}}
,{"type":"Feature","geometry":{"type":"Point","coordinates":[-112.0411928,43.4951494000001]},"properties":{"State":"ID","FCode":"74034","Feature":"Law Enforcement","OSM_ID":"1722388"}}
,{"type":"Feature","geometry":{"type":"Point","coordinates":[-111.3019832,42.318021]},"properties":{"State":"ID","FCode":"74034","Feature":"Law Enforcement","OSM_ID":"1722937"}}
,{"type":"Feature","geometry":{"type":"Point","coordinates":[-111.5990052,42.6549742]},"properties":{"State":"ID","FCode":"74034","Feature":"Law Enforcement","OSM_ID":"1723055"}}
,{"type":"Feature","geometry":{"type":"Point","coordinates":[-111.1106651,43.7242150000001]},"properties":{"State":"ID","FCode":"74034","Feature":"Law Enforcement","OSM_ID":"1723141"}}
,{"type":"Feature","geometry":{"type":"Point","coordinates":[-111.778605,43.8263784000001]},"properties":{"State":"ID","FCode":"74034","Feature":"Law Enforcement","OSM_ID":"1723248"}}
,{"type":"Feature","geometry":{"type":"Point","coordinates":[-112.3443789,43.1943898000001]},"properties":{"State":"ID","FCode":"74034","Feature":"Law Enforcement","OSM_ID":"1723269"}}
,{"type":"Feature","geometry":{"type":"Point","coordinates":[-111.9916941,43.4700688]},"properties":{"State":"ID","FCode":"80012","Feature":"Hospital / Medical Center","OSM_ID":"1723586"}}
,{"type":"Feature","geometry":{"type":"Point","coordinates":[-111.6146222,42.6515841]},"properties":{"State":"ID","FCode":"80012","Feature":"Hospital / Medical Center","OSM_ID":"1723935"}}
,{"type":"Feature","geometry":{"type":"Point","coordinates":[-112.3555335,43.1957676000001]},"properties":{"State":"ID","FCode":"80012","Feature":"Hospital / Medical Center","OSM_ID":"1724083"}}
,{"type":"Feature","geometry":{"type":"Point","coordinates":[-111.7709582,43.8256973000001]},"properties":{"State":"ID","FCode":"80012","Feature":"Hospital / Medical Center","OSM_ID":"1724304"}}
,{"type":"Feature","geometry":{"type":"Point","coordinates":[-112.2502199,42.1893383]},"properties":{"State":"ID","FCode":"80012","Feature":"Hospital / Medical Center","OSM_ID":"1724462"}}
,{"type":"Feature","geometry":{"type":"Point","coordinates":[-112.3469552,43.193294]},"properties":{"State":"ID","FCode":"80012","Feature":"Hospital / Medical Center","OSM_ID":"1724748"}}
,{"type":"Feature","geometry":{"type":"Point","coordinates":[-113.2952192,43.6395440000001]},"properties":{"State":"ID","FCode":"80012","Feature":"Hospital / Medical Center","OSM_ID":"1724950"}}
,{"type":"Feature","geometry":{"type":"Point","coordinates":[-111.3000792,42.3161969000001]},"properties":{"State":"ID","FCode":"80012","Feature":"Hospital / Medical Center","OSM_ID":"1725261"}}
,{"type":"Feature","geometry":{"type":"Point","coordinates":[-111.1081207,43.7270015]},"properties":{"State":"ID","FCode":"80012","Feature":"Hospital / Medical Center","OSM_ID":"1725267"}}
,{"type":"Feature","geometry":{"type":"Point","coordinates":[-111.8728909,42.0975931]},"properties":{"State":"ID","FCode":"80012","Feature":"Hospital / Medical Center","OSM_ID":"1725431"}}
,{"type":"Feature","geometry":{"type":"Point","coordinates":[-111.9880743,43.4742471000001]},"properties":{"State":"ID","FCode":"80012","Feature":"Hospital / Medical Center","OSM_ID":"1725451"}}
,{"type":"Feature","geometry":{"type":"Point","coordinates":[-112.342864,43.1869343000001]},"properties":{"State":"ID","FCode":"73002","Feature":"School","OSM_ID":"1731780"}}
,{"type":"Feature","geometry":{"type":"Point","coordinates":[-111.8010534,43.8105922]},"properties":{"State":"ID","FCode":"73002","Feature":"School","OSM_ID":"1732399"}}
,{"type":"Feature","geometry":{"type":"Point","coordinates":[-112.2304724,44.1727765000001]},"properties":{"State":"ID","FCode":"73002","Feature":"School","OSM_ID":"1732766"}}
,{"type":"Feature","geometry":{"type":"Point","coordinates":[-111.684686,43.9729056]},"properties":{"State":"ID","FCode":"73002","Feature":"School","OSM_ID":"1732767"}}
,{"type":"Feature","geometry":{"type":"Point","coordinates":[-112.1177764,42.4295379000001]},"properties":{"State":"ID","FCode":"73002","Feature":"School","OSM_ID":"1732822"}}
,{"type":"Feature","geometry":{"type":"Point","coordinates":[-112.2088836,43.9254495000001]},"properties":{"State":"ID","FCode":"73002","Feature":"School","OSM_ID":"1732931"}}
,{"type":"Feature","geometry":{"type":"Point","coordinates":[-116.6943885,44.5553536]},"properties":{"State":"ID","FCode":"73002","Feature":"School","OSM_ID":"1733036"}}
,{"type":"Feature","geometry":{"type":"Point","coordinates":[-111.6722716,43.8873721000001]},"properties":{"State":"ID","FCode":"73002","Feature":"School","OSM_ID":"1733070"}}
,{"type":"Feature","geometry":{"type":"Point","coordinates":[-111.5967708,42.6532869000001]},"properties":{"State":"ID","FCode":"73002","Feature":"School","OSM_ID":"1733320"}}
,{"type":"Feature","geometry":{"type":"Point","coordinates":[-111.4550174,44.0700653000001]},"properties":{"State":"ID","FCode":"73002","Feature":"School","OSM_ID":"1733717"}}
,{"type":"Feature","geometry":{"type":"Point","coordinates":[-111.2959602,42.3294482000001]},"properties":{"State":"ID","FCode":"73002","Feature":"School","OSM_ID":"1733749"}}
,{"type":"Feature","geometry":{"type":"Point","coordinates":[-111.8397904,43.8560881000001]},"properties":{"State":"ID","FCode":"73002","Feature":"School","OSM_ID":"1733873"}}
,{"type":"Feature","geometry":{"type":"Point","coordinates":[-112.0078942,43.4900382000001]},"properties":{"State":"ID","FCode":"73002","Feature":"School","OSM_ID":"1734274"}}
,{"type":"Feature","geometry":{"type":"Point","coordinates":[-112.0061046,43.7086575000001]},"properties":{"State":"ID","FCode":"73002","Feature":"School","OSM_ID":"1734275"}}
,{"type":"Feature","geometry":{"type":"Point","coordinates":[-111.688243,43.9579292000001]},"properties":{"State":"ID","FCode":"73002","Feature":"School","OSM_ID":"1734440"}}
,{"type":"Feature","geometry":{"type":"Point","coordinates":[-111.7150771,43.96916]},"properties":{"State":"ID","FCode":"73002","Feature":"School","OSM_ID":"1734447"}}
,{"type":"Feature","geometry":{"type":"Point","coordinates":[-111.4396054,44.0725478000001]},"properties":{"State":"ID","FCode":"73002","Feature":"School","OSM_ID":"1734700"}}
,{"type":"Feature","geometry":{"type":"Point","coordinates":[-111.0651483,42.3589332000001]},"properties":{"State":"ID","FCode":"73002","Feature":"School","OSM_ID":"1734753"}}
,{"type":"Feature","geometry":{"type":"Point","coordinates":[-113.3023833,43.6335797]},"properties":{"State":"ID","FCode":"73002","Feature":"School","OSM_ID":"1734782"}}
,{"type":"Feature","geometry":{"type":"Point","coordinates":[-112.0781035,43.4786689000001]},"properties":{"State":"ID","FCode":"73002","Feature":"School","OSM_ID":"1734898"}}
,{"type":"Feature","geometry":{"type":"Point","coordinates":[-112.0145091,43.5836009000001]},"properties":{"State":"ID","FCode":"73002","Feature":"School","OSM_ID":"1735094"}}
,{"type":"Feature","geometry":{"type":"Point","coordinates":[-113.00393,43.7850480000001]},"properties":{"State":"ID","FCode":"73002","Feature":"School","OSM_ID":"1735121"}}
,{"type":"Feature","geometry":{"type":"Point","coordinates":[-112.4358612,43.1459792000001]},"properties":{"State":"ID","FCode":"73002","Feature":"School","OSM_ID":"1735358"}}
,{"type":"Feature","geometry":{"type":"Point","coordinates":[-112.2297978,44.172782]},"properties":{"State":"ID","FCode":"73002","Feature":"School","OSM_ID":"1735396"}}
,{"type":"Feature","geometry":{"type":"Point","coordinates":[-111.1115053,43.7261512000001]},"properties":{"State":"ID","FCode":"73002","Feature":"School","OSM_ID":"1735758"}}
,{"type":"Feature","geometry":{"type":"Point","coordinates":[-112.069103,43.4916978000001]},"properties":{"State":"ID","FCode":"73002","Feature":"School","OSM_ID":"1735843"}}
,{"type":"Feature","geometry":{"type":"Point","coordinates":[-111.7744837,43.6293222]},"properties":{"State":"ID","FCode":"73002","Feature":"School","OSM_ID":"1735856"}}
,{"type":"Feature","geometry":{"type":"Point","coordinates":[-111.6846898,43.9729045]},"properties":{"State":"ID","FCode":"73002","Feature":"School","OSM_ID":"1736058"}}
,{"type":"Feature","geometry":{"type":"Point","coordinates":[-116.8643026,47.9540658000001]},"properties":{"State":"ID","FCode":"73002","Feature":"School","OSM_ID":"1736232"}}
,{"type":"Feature","geometry":{"type":"Point","coordinates":[-112.0040408,43.7175582]},"properties":{"State":"ID","FCode":"73002","Feature":"School","OSM_ID":"1736349"}}
,{"type":"Feature","geometry":{"type":"Point","coordinates":[-111.9652911,43.5266156000001]},"properties":{"State":"ID","FCode":"73002","Feature":"School","OSM_ID":"1736769"}}
,{"type":"Feature","geometry":{"type":"Point","coordinates":[-111.0993339,43.7312928000001]},"properties":{"State":"ID","FCode":"73002","Feature":"School","OSM_ID":"1737347"}}
,{"type":"Feature","geometry":{"type":"Point","coordinates":[-111.1098586,43.7299967000001]},"properties":{"State":"ID","FCode":"73002","Feature":"School","OSM_ID":"1737384"}}
,{"type":"Feature","geometry":{"type":"Point","coordinates":[-111.9753786,43.4914979000001]},"properties":{"State":"ID","FCode":"73002","Feature":"School","OSM_ID":"1737475"}}
,{"type":"Feature","geometry":{"type":"Point","coordinates":[-116.8634057,47.9566407]},"properties":{"State":"ID","FCode":"73002","Feature":"School","OSM_ID":"1737484"}}
,{"type":"Feature","geometry":{"type":"Point","coordinates":[-111.7307342,42.4071452000001]},"properties":{"State":"ID","FCode":"73002","Feature":"School","OSM_ID":"1737735"}}
,{"type":"Feature","geometry":{"type":"Point","coordinates":[-111.1099053,43.7299712000001]},"properties":{"State":"ID","FCode":"73002","Feature":"School","OSM_ID":"1737826"}}
,{"type":"Feature","geometry":{"type":"Point","coordinates":[-112.0146193,43.4992636000001]},"properties":{"State":"ID","FCode":"73002","Feature":"School","OSM_ID":"1737900"}}
,{"type":"Feature","geometry":{"type":"Point","coordinates":[-112.2419923,42.1796907]},"properties":{"State":"ID","FCode":"73002","Feature":"School","OSM_ID":"1738349"}}
,{"type":"Feature","geometry":{"type":"Point","coordinates":[-112.0278927,43.4600127000001]},"properties":{"State":"ID","FCode":"73002","Feature":"School","OSM_ID":"1738627"}}
,{"type":"Feature","geometry":{"type":"Point","coordinates":[-115.4353521,45.8283284]},"properties":{"State":"ID","FCode":"73002","Feature":"School","OSM_ID":"1738755"}}
,{"type":"Feature","geometry":{"type":"Point","coordinates":[-112.0371238,43.5118714000001]},"properties":{"State":"ID","FCode":"73002","Feature":"School","OSM_ID":"1738964"}}
,{"type":"Feature","geometry":{"type":"Point","coordinates":[-111.9514366,43.5932728000001]},"properties":{"State":"ID","FCode":"73002","Feature":"School","OSM_ID":"1739012"}}
,{"type":"Feature","geometry":{"type":"Point","coordinates":[-112.3631893,43.1882603]},"properties":{"State":"ID","FCode":"73002","Feature":"School","OSM_ID":"1739374"}}
,{"type":"Feature","geometry":{"type":"Point","coordinates":[-116.8695123,47.9696657000001]},"properties":{"State":"ID","FCode":"73002","Feature":"School","OSM_ID":"1739418"}}
,{"type":"Feature","geometry":{"type":"Point","coordinates":[-111.7321303,42.5724273000001]},"properties":{"State":"ID","FCode":"73002","Feature":"School","OSM_ID":"1739437"}}
,{"type":"Feature","geometry":{"type":"Point","coordinates":[-113.6408269,44.9573989]},"properties":{"State":"ID","FCode":"73002","Feature":"School","OSM_ID":"1739453"}}
,{"type":"Feature","geometry":{"type":"Point","coordinates":[-111.7392788,43.8721186000001]},"properties":{"State":"ID","FCode":"73002","Feature":"School","OSM_ID":"1739456"}}
,{"type":"Feature","geometry":{"type":"Point","coordinates":[-112.0063,43.4832900000001]},"properties":{"State":"ID","FCode":"73002","Feature":"School","OSM_ID":"1739521"}}
,{"type":"Feature","geometry":{"type":"Point","coordinates":[-114.6861796,42.5138353]},"properties":{"State":"ID","FCode":"73002","Feature":"School","OSM_ID":"1739581"}}
,{"type":"Feature","geometry":{"type":"Point","coordinates":[-111.9771236,43.4706865000001]},"properties":{"State":"ID","FCode":"73002","Feature":"School","OSM_ID":"1739647"}}
,{"type":"Feature","geometry":{"type":"Point","coordinates":[-114.7906627,43.3471664]},"properties":{"State":"ID","FCode":"73002","Feature":"School","OSM_ID":"1739665"}}
,{"type":"Feature","geometry":{"type":"Point","coordinates":[-112.0263,43.4753000000001]},"properties":{"State":"ID","FCode":"73002","Feature":"School","OSM_ID":"1739714"}}
,{"type":"Feature","geometry":{"type":"Point","coordinates":[-112.4355452,43.1943797000001]},"properties":{"State":"ID","FCode":"73002","Feature":"School","OSM_ID":"1739792"}}
,{"type":"Feature","geometry":{"type":"Point","coordinates":[-111.9936225,43.5396400000001]},"properties":{"State":"ID","FCode":"73002","Feature":"School","OSM_ID":"1739976"}}
,{"type":"Feature","geometry":{"type":"Point","coordinates":[-112.0339457,43.4910393000001]},"properties":{"State":"ID","FCode":"73002","Feature":"School","OSM_ID":"1740442"}}
,{"type":"Feature","geometry":{"type":"Point","coordinates":[-111.9644554,43.5275984]},"properties":{"State":"ID","FCode":"73002","Feature":"School","OSM_ID":"1740662"}}
,{"type":"Feature","geometry":{"type":"Point","coordinates":[-112.0094,43.4802800000001]},"properties":{"State":"ID","FCode":"73002","Feature":"School","OSM_ID":"1741012"}}
,{"type":"Feature","geometry":{"type":"Point","coordinates":[-115.81273,47.2503223000001]},"properties":{"State":"ID","FCode":"73002","Feature":"School","OSM_ID":"1741422"}}
,{"type":"Feature","geometry":{"type":"Point","coordinates":[-111.8757214,42.1066305000001]},"properties":{"State":"ID","FCode":"73002","Feature":"School","OSM_ID":"1741489"}}
,{"type":"Feature","geometry":{"type":"Point","coordinates":[-111.1582932,43.8129052]},"properties":{"State":"ID","FCode":"73002","Feature":"School","OSM_ID":"1741518"}}
,{"type":"Feature","geometry":{"type":"Point","coordinates":[-113.5561886,43.5557929]},"properties":{"State":"ID","FCode":"73002","Feature":"School","OSM_ID":"1742261"}}
,{"type":"Feature","geometry":{"type":"Point","coordinates":[-111.0831392,43.7301683000001]},"properties":{"State":"WY","FCode":"73002","Feature":"School","OSM_ID":"1742299"}}
,{"type":"Feature","geometry":{"type":"Point","coordinates":[-111.9910744,43.4869884]},"properties":{"State":"ID","FCode":"73002","Feature":"School","OSM_ID":"1742350"}}
,{"type":"Feature","geometry":{"type":"Point","coordinates":[-112.5958652,43.1156695000001]},"properties":{"State":"ID","FCode":"73002","Feature":"School","OSM_ID":"1742581"}}
,{"type":"Feature","geometry":{"type":"Point","coordinates":[-111.9717783,43.4955805000001]},"properties":{"State":"ID","FCode":"73002","Feature":"School","OSM_ID":"1742608"}}
,{"type":"Feature","geometry":{"type":"Point","coordinates":[-112.6957924,42.0246040000001]},"properties":{"State":"ID","FCode":"73002","Feature":"School","OSM_ID":"1742636"}}
,{"type":"Feature","geometry":{"type":"Point","coordinates":[-111.926482,43.5247189]},"properties":{"State":"ID","FCode":"73002","Feature":"School","OSM_ID":"1742664"}}
,{"type":"Feature","geometry":{"type":"Point","coordinates":[-111.9850129,43.4980171]},"properties":{"State":"ID","FCode":"73002","Feature":"School","OSM_ID":"1742728"}}
,{"type":"Feature","geometry":{"type":"Point","coordinates":[-111.684437,43.9722386]},"properties":{"State":"ID","FCode":"73002","Feature":"School","OSM_ID":"1742755"}}
,{"type":"Feature","geometry":{"type":"Point","coordinates":[-111.7986151,43.8246076]},"properties":{"State":"ID","FCode":"73002","Feature":"School","OSM_ID":"1743080"}}
,{"type":"Feature","geometry":{"type":"Point","coordinates":[-111.7828,43.7161938]},"properties":{"State":"ID","FCode":"73002","Feature":"School","OSM_ID":"1743601"}}
,{"type":"Feature","geometry":{"type":"Point","coordinates":[-112.0123833,43.5012391000001]},"properties":{"State":"ID","FCode":"73002","Feature":"School","OSM_ID":"1743949"}}
,{"type":"Feature","geometry":{"type":"Point","coordinates":[-111.3694783,42.4775797]},"properties":{"State":"ID","FCode":"73002","Feature":"School","OSM_ID":"1743959"}}
,{"type":"Feature","geometry":{"type":"Point","coordinates":[-116.7294671,44.4706692]},"properties":{"State":"ID","FCode":"73002","Feature":"School","OSM_ID":"1744393"}}
,{"type":"Feature","geometry":{"type":"Point","coordinates":[-111.938127,43.5078041]},"properties":{"State":"ID","FCode":"73002","Feature":"School","OSM_ID":"1744500"}}
,{"type":"Feature","geometry":{"type":"Point","coordinates":[-111.9947151,43.4875048000001]},"properties":{"State":"ID","FCode":"73002","Feature":"School","OSM_ID":"1744643"}}
,{"type":"Feature","geometry":{"type":"Point","coordinates":[-111.9355556,43.4772061]},"properties":{"State":"ID","FCode":"73002","Feature":"School","OSM_ID":"1744920"}}
,{"type":"Feature","geometry":{"type":"Point","coordinates":[-111.7395752,43.875996]},"properties":{"State":"ID","FCode":"73002","Feature":"School","OSM_ID":"1745060"}}
,{"type":"Feature","geometry":{"type":"Point","coordinates":[-111.7692222,43.8292724]},"properties":{"State":"ID","FCode":"73002","Feature":"School","OSM_ID":"1745219"}}
,{"type":"Feature","geometry":{"type":"Point","coordinates":[-115.9743979,46.1461534000001]},"properties":{"State":"ID","FCode":"73002","Feature":"School","OSM_ID":"1745221"}}
,{"type":"Feature","geometry":{"type":"Point","coordinates":[-112.4783203,43.1989155000001]},"properties":{"State":"ID","FCode":"73002","Feature":"School","OSM_ID":"1745543"}}
,{"type":"Feature","geometry":{"type":"Point","coordinates":[-112.1305503,43.7246756000001]},"properties":{"State":"ID","FCode":"73002","Feature":"School","OSM_ID":"1745776"}}
,{"type":"Feature","geometry":{"type":"Point","coordinates":[-111.7730555,43.8211321000001]},"properties":{"State":"ID","FCode":"73002","Feature":"School","OSM_ID":"1745808"}}
,{"type":"Feature","geometry":{"type":"Point","coordinates":[-112.3449663,43.1801303]},"properties":{"State":"ID","FCode":"73002","Feature":"School","OSM_ID":"1746063"}}
,{"type":"Feature","geometry":{"type":"Point","coordinates":[-112.0280129,43.493657]},"properties":{"State":"ID","FCode":"73002","Feature":"School","OSM_ID":"1746963"}}
,{"type":"Feature","geometry":{"type":"Point","coordinates":[-112.4450755,43.8403511000001]},"properties":{"State":"ID","FCode":"73002","Feature":"School","OSM_ID":"1747281"}}
,{"type":"Feature","geometry":{"type":"Point","coordinates":[-111.9536084,43.5041037]},"properties":{"State":"ID","FCode":"73002","Feature":"School","OSM_ID":"1747351"}}
,{"type":"Feature","geometry":{"type":"Point","coordinates":[-111.3989296,42.2264152000001]},"properties":{"State":"ID","FCode":"73002","Feature":"School","OSM_ID":"1747385"}}
,{"type":"Feature","geometry":{"type":"Point","coordinates":[-112.0191445,43.4932007]},"properties":{"State":"ID","FCode":"73002","Feature":"School","OSM_ID":"1747482"}}
,{"type":"Feature","geometry":{"type":"Point","coordinates":[-111.7428262,43.8749148000001]},"properties":{"State":"ID","FCode":"73002","Feature":"School","OSM_ID":"1747554"}}
,{"type":"Feature","geometry":{"type":"Point","coordinates":[-111.9739,43.47533]},"properties":{"State":"ID","FCode":"73002","Feature":"School","OSM_ID":"1747663"}}
,{"type":"Feature","geometry":{"type":"Point","coordinates":[-116.7291404,44.4710858]},"properties":{"State":"ID","FCode":"73002","Feature":"School","OSM_ID":"1747883"}}
,{"type":"Feature","geometry":{"type":"Point","coordinates":[-115.4353509,45.8283295000001]},"properties":{"State":"ID","FCode":"73002","Feature":"School","OSM_ID":"1748097"}}
,{"type":"Feature","geometry":{"type":"Point","coordinates":[-111.9305703,43.7276525]},"properties":{"State":"ID","FCode":"73002","Feature":"School","OSM_ID":"1748520"}}
,{"type":"Feature","geometry":{"type":"Point","coordinates":[-115.3099885,42.9587944]},"properties":{"State":"ID","FCode":"73002","Feature":"School","OSM_ID":"1748636"}}
,{"type":"Feature","geometry":{"type":"Point","coordinates":[-112.0156254,42.6164872000001]},"properties":{"State":"ID","FCode":"73002","Feature":"School","OSM_ID":"1748893"}}
,{"type":"Feature","geometry":{"type":"Point","coordinates":[-112.2404493,42.1797608000001]},"properties":{"State":"ID","FCode":"73002","Feature":"School","OSM_ID":"1749023"}}
,{"type":"Feature","geometry":{"type":"Point","coordinates":[-111.9884793,43.4756373000001]},"properties":{"State":"ID","FCode":"73002","Feature":"School","OSM_ID":"1749147"}}
,{"type":"Feature","geometry":{"type":"Point","coordinates":[-116.553766,48.2025861000001]},"properties":{"State":"ID","FCode":"73002","Feature":"School","OSM_ID":"1750142"}}
,{"type":"Feature","geometry":{"type":"Point","coordinates":[-111.7773798,43.8136121000001]},"properties":{"State":"ID","FCode":"73002","Feature":"School","OSM_ID":"1750392"}}
,{"type":"Feature","geometry":{"type":"Point","coordinates":[-112.1814683,42.5807265]},"properties":{"State":"ID","FCode":"73002","Feature":"School","OSM_ID":"1750413"}}
,{"type":"Feature","geometry":{"type":"Point","coordinates":[-112.3320023,43.1900949000001]},"properties":{"State":"ID","FCode":"73002","Feature":"School","OSM_ID":"1750449"}}
,{"type":"Feature","geometry":{"type":"Point","coordinates":[-112.2302389,44.1701489000001]},"properties":{"State":"ID","FCode":"73002","Feature":"School","OSM_ID":"1750716"}}
,{"type":"Feature","geometry":{"type":"Point","coordinates":[-116.1309277,45.9186879000001]},"properties":{"State":"ID","FCode":"73002","Feature":"School","OSM_ID":"1750922"}}
,{"type":"Feature","geometry":{"type":"Point","coordinates":[-111.1072988,43.7234095000001]},"properties":{"State":"ID","FCode":"73002","Feature":"School","OSM_ID":"1750934"}}
,{"type":"Feature","geometry":{"type":"Point","coordinates":[-111.6842664,43.9749945]},"properties":{"State":"ID","FCode":"73002","Feature":"School","OSM_ID":"1751183"}}
,{"type":"Feature","geometry":{"type":"Point","coordinates":[-112.0672961,43.4869570000001]},"properties":{"State":"ID","FCode":"73002","Feature":"School","OSM_ID":"1751269"}}
,{"type":"Feature","geometry":{"type":"Point","coordinates":[-112.8724793,42.5747061000001]},"properties":{"State":"ID","FCode":"73002","Feature":"School","OSM_ID":"1751296"}}
,{"type":"Feature","geometry":{"type":"Point","coordinates":[-112.0230919,43.4924929000001]},"properties":{"State":"ID","FCode":"73002","Feature":"School","OSM_ID":"1751319"}}
,{"type":"Feature","geometry":{"type":"Point","coordinates":[-111.7392755,43.8721265]},"properties":{"State":"ID","FCode":"73002","Feature":"School","OSM_ID":"1751486"}}
,{"type":"Feature","geometry":{"type":"Point","coordinates":[-111.3041026,42.3163551000001]},"properties":{"State":"ID","FCode":"73002","Feature":"School","OSM_ID":"1751522"}}
,{"type":"Feature","geometry":{"type":"Point","coordinates":[-111.8657048,42.086781]},"properties":{"State":"ID","FCode":"73002","Feature":"School","OSM_ID":"1751529"}}
,{"type":"Feature","geometry":{"type":"Point","coordinates":[-111.9617028,43.6707947]},"properties":{"State":"ID","FCode":"73002","Feature":"School","OSM_ID":"1751949"}}
,{"type":"Feature","geometry":{"type":"Point","coordinates":[-111.7312047,42.5703652]},"properties":{"State":"ID","FCode":"73002","Feature":"School","OSM_ID":"1752243"}}
,{"type":"Feature","geometry":{"type":"Point","coordinates":[-114.7912354,43.3471260000001]},"properties":{"State":"ID","FCode":"73002","Feature":"School","OSM_ID":"1752454"}}
,{"type":"Feature","geometry":{"type":"Point","coordinates":[-113.3015672,43.6331068000001]},"properties":{"State":"ID","FCode":"73002","Feature":"School","OSM_ID":"1752581"}}
,{"type":"Feature","geometry":{"type":"Point","coordinates":[-115.3855925,43.4726564000001]},"properties":{"State":"ID","FCode":"73002","Feature":"School","OSM_ID":"1752637"}}
,{"type":"Feature","geometry":{"type":"Point","coordinates":[-112.0681865,43.4903526000001]},"properties":{"State":"ID","FCode":"73002","Feature":"School","OSM_ID":"1752746"}}
,{"type":"Feature","geometry":{"type":"Point","coordinates":[-112.0164512,43.5155419000001]},"properties":{"State":"ID","FCode":"73002","Feature":"School","OSM_ID":"1753106"}}
,{"type":"Feature","geometry":{"type":"Point","coordinates":[-111.106931,43.7279985000001]},"properties":{"State":"ID","FCode":"73002","Feature":"School","OSM_ID":"1753140"}}
,{"type":"Feature","geometry":{"type":"Point","coordinates":[-111.5928996,42.6622005]},"properties":{"State":"ID","FCode":"73002","Feature":"School","OSM_ID":"1753533"}}
,{"type":"Feature","geometry":{"type":"Point","coordinates":[-115.8327129,43.8310208]},"properties":{"State":"ID","FCode":"73002","Feature":"School","OSM_ID":"1754549"}}
,{"type":"Feature","geometry":{"type":"Point","coordinates":[-112.3534,43.19615]},"properties":{"State":"ID","FCode":"73002","Feature":"School","OSM_ID":"1754581"}}
,{"type":"Feature","geometry":{"type":"Point","coordinates":[-112.3392,43.1901100000001]},"properties":{"State":"ID","FCode":"73002","Feature":"School","OSM_ID":"1754595"}}
,{"type":"Feature","geometry":{"type":"Point","coordinates":[-111.9611312,43.4550529000001]},"properties":{"State":"ID","FCode":"73002","Feature":"School","OSM_ID":"1754786"}}
,{"type":"Feature","geometry":{"type":"Point","coordinates":[-113.9423288,43.312684]},"properties":{"State":"ID","FCode":"73002","Feature":"School","OSM_ID":"1755117"}}
,{"type":"Feature","geometry":{"type":"Point","coordinates":[-111.7775603,43.8286718000001]},"properties":{"State":"ID","FCode":"73002","Feature":"School","OSM_ID":"1755194"}}
,{"type":"Feature","geometry":{"type":"Point","coordinates":[-111.9183619,43.6725853]},"properties":{"State":"ID","FCode":"73002","Feature":"School","OSM_ID":"1755213"}}
,{"type":"Feature","geometry":{"type":"Point","coordinates":[-115.8336536,43.8318591]},"properties":{"State":"ID","FCode":"73002","Feature":"School","OSM_ID":"1755225"}}
,{"type":"Feature","geometry":{"type":"Point","coordinates":[-111.965338,43.6710082000001]},"properties":{"State":"ID","FCode":"73002","Feature":"School","OSM_ID":"1755448"}}
,{"type":"Feature","geometry":{"type":"Point","coordinates":[-112.3454753,43.2026272000001]},"properties":{"State":"ID","FCode":"73002","Feature":"School","OSM_ID":"1756284"}}
,{"type":"Feature","geometry":{"type":"Point","coordinates":[-112.1814665,42.5807235]},"properties":{"State":"ID","FCode":"73002","Feature":"School","OSM_ID":"1756534"}}
,{"type":"Feature","geometry":{"type":"Point","coordinates":[-111.777564,43.8178528]},"properties":{"State":"ID","FCode":"73002","Feature":"School","OSM_ID":"1756538"}}
,{"type":"Feature","geometry":{"type":"Point","coordinates":[-111.7491415,43.8734152000001]},"properties":{"State":"ID","FCode":"73002","Feature":"School","OSM_ID":"1756831"}}
,{"type":"Feature","geometry":{"type":"Point","coordinates":[-112.0061185,43.7086439]},"properties":{"State":"ID","FCode":"73002","Feature":"School","OSM_ID":"1756995"}}
,{"type":"Feature","geometry":{"type":"Point","coordinates":[-112.4433413,43.8407636000001]},"properties":{"State":"ID","FCode":"73002","Feature":"School","OSM_ID":"1757110"}}
,{"type":"Feature","geometry":{"type":"Point","coordinates":[-112.0845231,43.4848551000001]},"properties":{"State":"ID","FCode":"73002","Feature":"School","OSM_ID":"1757149"}}
,{"type":"Feature","geometry":{"type":"Point","coordinates":[-112.5062027,43.1810688]},"properties":{"State":"ID","FCode":"73002","Feature":"School","OSM_ID":"1757357"}}
,{"type":"Feature","geometry":{"type":"Point","coordinates":[-111.9853901,43.4592071000001]},"properties":{"State":"ID","FCode":"73002","Feature":"School","OSM_ID":"1757439"}}
,{"type":"Feature","geometry":{"type":"Point","coordinates":[-111.9686304,43.5118086000001]},"properties":{"State":"ID","FCode":"73002","Feature":"School","OSM_ID":"1757582"}}
,{"type":"Feature","geometry":{"type":"Point","coordinates":[-112.034109,43.492402]},"properties":{"State":"ID","FCode":"73002","Feature":"School","OSM_ID":"1757935"}}
,{"type":"Feature","geometry":{"type":"Point","coordinates":[-112.3458302,43.1793342]},"properties":{"State":"ID","FCode":"73002","Feature":"School","OSM_ID":"1758088"}}
,{"type":"Feature","geometry":{"type":"Point","coordinates":[-111.3018006,42.3207753]},"properties":{"State":"ID","FCode":"73002","Feature":"School","OSM_ID":"1758147"}}
,{"type":"Feature","geometry":{"type":"Point","coordinates":[-112.5540353,42.5605529000001]},"properties":{"State":"ID","FCode":"73002","Feature":"School","OSM_ID":"1758296"}}
,{"type":"Feature","geometry":{"type":"Point","coordinates":[-112.0319537,43.4900534000001]},"properties":{"State":"ID","FCode":"73002","Feature":"School","OSM_ID":"1758717"}}
,{"type":"Feature","geometry":{"type":"Point","coordinates":[-111.2932,43.4057971]},"properties":{"State":"ID","FCode":"73002","Feature":"School","OSM_ID":"1759148"}}
,{"type":"Feature","geometry":{"type":"Point","coordinates":[-112.1804488,42.5783466]},"properties":{"State":"ID","FCode":"73002","Feature":"School","OSM_ID":"1759186"}}
,{"type":"Feature","geometry":{"type":"Point","coordinates":[-111.785277,43.8264064000001]},"properties":{"State":"ID","FCode":"73002","Feature":"School","OSM_ID":"1759332"}}
,{"type":"Feature","geometry":{"type":"Point","coordinates":[-116.566785,43.5576727000001]},"properties":{"State":"ID","FCode":"73002","Feature":"School","OSM_ID":"1759509"}}
,{"type":"Feature","geometry":{"type":"Point","coordinates":[-112.5230667,43.2004839000001]},"properties":{"State":"ID","FCode":"73002","Feature":"School","OSM_ID":"1759900"}}
,{"type":"Feature","geometry":{"type":"Point","coordinates":[-111.6986236,43.9439859]},"properties":{"State":"ID","FCode":"73002","Feature":"School","OSM_ID":"1759931"}}
,{"type":"Feature","geometry":{"type":"Point","coordinates":[-111.8571236,43.8017775000001]},"properties":{"State":"ID","FCode":"73002","Feature":"School","OSM_ID":"1760358"}}
,{"type":"Feature","geometry":{"type":"Point","coordinates":[-111.872616,42.0925330000001]},"properties":{"State":"ID","FCode":"73002","Feature":"School","OSM_ID":"1760441"}}
,{"type":"Feature","geometry":{"type":"Point","coordinates":[-111.5955987,42.6528063000001]},"properties":{"State":"ID","FCode":"73002","Feature":"School","OSM_ID":"1760527"}}
,{"type":"Feature","geometry":{"type":"Point","coordinates":[-111.8869032,42.7171186]},"properties":{"State":"ID","FCode":"73002","Feature":"School","OSM_ID":"1761088"}}
,{"type":"Feature","geometry":{"type":"Point","coordinates":[-111.9174298,43.6791644]},"properties":{"State":"ID","FCode":"73002","Feature":"School","OSM_ID":"1761114"}}
,{"type":"Feature","geometry":{"type":"Point","coordinates":[-114.5953006,42.2150589]},"properties":{"State":"ID","FCode":"73002","Feature":"School","OSM_ID":"1761183"}}
,{"type":"Feature","geometry":{"type":"Point","coordinates":[-115.4353521,45.8283253000001]},"properties":{"State":"ID","FCode":"73002","Feature":"School","OSM_ID":"1761336"}}
,{"type":"Feature","geometry":{"type":"Point","coordinates":[-116.6823722,44.5741527000001]},"properties":{"State":"ID","FCode":"73002","Feature":"School","OSM_ID":"1761356"}}
,{"type":"Feature","geometry":{"type":"Point","coordinates":[-111.7762728,43.6205546]},"properties":{"State":"ID","FCode":"73002","Feature":"School","OSM_ID":"1761711"}}
,{"type":"Feature","geometry":{"type":"Point","coordinates":[-112.0553784,43.5002511000001]},"properties":{"State":"ID","FCode":"73002","Feature":"School","OSM_ID":"1761723"}}
,{"type":"Feature","geometry":{"type":"Point","coordinates":[-111.8646568,42.0828588000001]},"properties":{"State":"ID","FCode":"73002","Feature":"School","OSM_ID":"1761852"}}
,{"type":"Feature","geometry":{"type":"Point","coordinates":[-113.3608833,44.6778034000001]},"properties":{"State":"ID","FCode":"73002","Feature":"School","OSM_ID":"1762297"}}
,{"type":"Feature","geometry":{"type":"Point","coordinates":[-111.9421904,43.6683844]},"properties":{"State":"ID","FCode":"73002","Feature":"School","OSM_ID":"1762428"}}
,{"type":"Feature","geometry":{"type":"Point","coordinates":[-112.252006,42.1948473]},"properties":{"State":"ID","FCode":"73002","Feature":"School","OSM_ID":"1762519"}}
,{"type":"Feature","geometry":{"type":"Point","coordinates":[-111.6872221,43.971121]},"properties":{"State":"ID","FCode":"73002","Feature":"School","OSM_ID":"1763584"}}
,{"type":"Feature","geometry":{"type":"Point","coordinates":[-111.9907743,42.1087198000001]},"properties":{"State":"ID","FCode":"73002","Feature":"School","OSM_ID":"1764314"}}
,{"type":"Feature","geometry":{"type":"Point","coordinates":[-115.3099845,42.9588035]},"properties":{"State":"ID","FCode":"73002","Feature":"School","OSM_ID":"1764373"}}
,{"type":"Feature","geometry":{"type":"Point","coordinates":[-115.5744095,43.5027506000001]},"properties":{"State":"ID","FCode":"73002","Feature":"School","OSM_ID":"1764583"}}
,{"type":"Feature","geometry":{"type":"Point","coordinates":[-111.1099351,43.6030937]},"properties":{"State":"ID","FCode":"73002","Feature":"School","OSM_ID":"1764736"}}
,{"type":"Feature","geometry":{"type":"Point","coordinates":[-111.7585901,43.9608036000001]},"properties":{"State":"ID","FCode":"73002","Feature":"School","OSM_ID":"1764781"}}
,{"type":"Feature","geometry":{"type":"Point","coordinates":[-111.1064546,43.7269878000001]},"properties":{"State":"ID","FCode":"73002","Feature":"School","OSM_ID":"1764846"}}
,{"type":"Feature","geometry":{"type":"Point","coordinates":[-111.6020759,42.6493825000001]},"properties":{"State":"ID","FCode":"73002","Feature":"School","OSM_ID":"1764909"}}
,{"type":"Feature","geometry":{"type":"Point","coordinates":[-116.5555129,43.5449133000001]},"properties":{"State":"ID","FCode":"73002","Feature":"School","OSM_ID":"1765008"}}
,{"type":"Feature","geometry":{"type":"Point","coordinates":[-111.8880493,42.7175358000001]},"properties":{"State":"ID","FCode":"73002","Feature":"School","OSM_ID":"1765220"}}
,{"type":"Feature","geometry":{"type":"Point","coordinates":[-112.3196582,43.2118809]},"properties":{"State":"ID","FCode":"73002","Feature":"School","OSM_ID":"1765482"}}
,{"type":"Feature","geometry":{"type":"Point","coordinates":[-112.192903,42.649094]},"properties":{"State":"ID","FCode":"73002","Feature":"School","OSM_ID":"1765670"}}
,{"type":"Feature","geometry":{"type":"Point","coordinates":[-111.990619,42.108261]},"properties":{"State":"ID","FCode":"73002","Feature":"School","OSM_ID":"1765692"}}
,{"type":"Feature","geometry":{"type":"Point","coordinates":[-112.3504831,43.1860070000001]},"properties":{"State":"ID","FCode":"73002","Feature":"School","OSM_ID":"1765772"}}
,{"type":"Feature","geometry":{"type":"Point","coordinates":[-111.303446,42.31715]},"properties":{"State":"ID","FCode":"73002","Feature":"School","OSM_ID":"1765787"}}
,{"type":"Feature","geometry":{"type":"Point","coordinates":[-112.3505293,43.1905545000001]},"properties":{"State":"ID","FCode":"73002","Feature":"School","OSM_ID":"1765824"}}
,{"type":"Feature","geometry":{"type":"Point","coordinates":[-111.9746642,43.4952481]},"properties":{"State":"ID","FCode":"73002","Feature":"School","OSM_ID":"1766004"}}
,{"type":"Feature","geometry":{"type":"Point","coordinates":[-111.9716768,43.5271478000001]},"properties":{"State":"ID","FCode":"73002","Feature":"School","OSM_ID":"1766103"}}
,{"type":"Feature","geometry":{"type":"Point","coordinates":[-112.3714954,43.220451]},"properties":{"State":"ID","FCode":"73002","Feature":"School","OSM_ID":"1766351"}}
,{"type":"Feature","geometry":{"type":"Point","coordinates":[-112.0717977,43.4902395]},"properties":{"State":"ID","FCode":"73002","Feature":"School","OSM_ID":"1766483"}}
,{"type":"Feature","geometry":{"type":"Point","coordinates":[-112.2585333,43.2463154000001]},"properties":{"State":"ID","FCode":"73002","Feature":"School","OSM_ID":"1766724"}}
,{"type":"Feature","geometry":{"type":"Point","coordinates":[-113.3051954,43.6389371000001]},"properties":{"State":"ID","FCode":"73002","Feature":"School","OSM_ID":"1767127"}}
,{"type":"Feature","geometry":{"type":"Point","coordinates":[-112.2419962,42.1796883000001]},"properties":{"State":"ID","FCode":"73002","Feature":"School","OSM_ID":"1767193"}}
,{"type":"Feature","geometry":{"type":"Point","coordinates":[-112.444362,43.2242428000001]},"properties":{"State":"ID","FCode":"73002","Feature":"School","OSM_ID":"1767443"}}
,{"type":"Feature","geometry":{"type":"Point","coordinates":[-111.8338483,43.7542137]},"properties":{"State":"ID","FCode":"73002","Feature":"School","OSM_ID":"1767786"}}
,{"type":"Feature","geometry":{"type":"Point","coordinates":[-112.0352942,43.4634837]},"properties":{"State":"ID","FCode":"73002","Feature":"School","OSM_ID":"1767801"}}
,{"type":"Feature","geometry":{"type":"Point","coordinates":[-111.8655142,42.0874605000001]},"properties":{"State":"ID","FCode":"73002","Feature":"School","OSM_ID":"1769057"}}
,{"type":"Feature","geometry":{"type":"Point","coordinates":[-115.6193174,44.0858341000001]},"properties":{"State":"ID","FCode":"73002","Feature":"School","OSM_ID":"1769156"}}
,{"type":"Feature","geometry":{"type":"Point","coordinates":[-111.774425,43.6327154000001]},"properties":{"State":"ID","FCode":"73002","Feature":"School","OSM_ID":"1769195"}}
,{"type":"Feature","geometry":{"type":"Point","coordinates":[-112.4786847,43.1982659000001]},"properties":{"State":"ID","FCode":"73002","Feature":"School","OSM_ID":"1769206"}}
,{"type":"Feature","geometry":{"type":"Point","coordinates":[-112.335035,43.1855731000001]},"properties":{"State":"ID","FCode":"73002","Feature":"School","OSM_ID":"1769485"}}
,{"type":"Feature","geometry":{"type":"Point","coordinates":[-111.7775656,43.8178367]},"properties":{"State":"ID","FCode":"73002","Feature":"School","OSM_ID":"1769615"}}
,{"type":"Feature","geometry":{"type":"Point","coordinates":[-111.9671,43.47146]},"properties":{"State":"ID","FCode":"73002","Feature":"School","OSM_ID":"1769633"}}
,{"type":"Feature","geometry":{"type":"Point","coordinates":[-111.9942423,42.1101596]},"properties":{"State":"ID","FCode":"73002","Feature":"School","OSM_ID":"1769697"}}
,{"type":"Feature","geometry":{"type":"Point","coordinates":[-112.0339,43.4839700000001]},"properties":{"State":"ID","FCode":"73002","Feature":"School","OSM_ID":"1769906"}}
,{"type":"Feature","geometry":{"type":"Point","coordinates":[-111.9757189,43.4734437000001]},"properties":{"State":"ID","FCode":"73002","Feature":"School","OSM_ID":"1769933"}}
,{"type":"Feature","geometry":{"type":"Point","coordinates":[-116.6800534,44.574751]},"properties":{"State":"ID","FCode":"73002","Feature":"School","OSM_ID":"1769949"}}
,{"type":"Feature","geometry":{"type":"Point","coordinates":[-111.0831392,43.7301683000001]},"properties":{"State":"WY","FCode":"73002","Feature":"School","OSM_ID":"1850389"}}
,{"type":"Feature","geometry":{"type":"Point","coordinates":[-116.2137454,43.5676742000001]},"properties":{"State":"ID","FCode":"78006","Feature":"Post Office","OSM_ID":"2063964"}}
,{"type":"Feature","geometry":{"type":"Point","coordinates":[-112.3458264,43.190438]},"properties":{"State":"ID","FCode":"78006","Feature":"Post Office","OSM_ID":"2063979"}}
,{"type":"Feature","geometry":{"type":"Point","coordinates":[-111.2948769,43.4062115]},"properties":{"State":"ID","FCode":"78006","Feature":"Post Office","OSM_ID":"2064071"}}
,{"type":"Feature","geometry":{"type":"Point","coordinates":[-112.4509751,42.9104108000001]},"properties":{"State":"ID","FCode":"78006","Feature":"Post Office","OSM_ID":"2064102"}}
,{"type":"Feature","geometry":{"type":"Point","coordinates":[-112.5362225,43.9662391000001]},"properties":{"State":"ID","FCode":"78006","Feature":"Post Office","OSM_ID":"2064202"}}
,{"type":"Feature","geometry":{"type":"Point","coordinates":[-111.8015188,42.0174923000001]},"properties":{"State":"ID","FCode":"78006","Feature":"Post Office","OSM_ID":"2064219"}}
,{"type":"Feature","geometry":{"type":"Point","coordinates":[-112.1243293,42.4290330000001]},"properties":{"State":"ID","FCode":"78006","Feature":"Post Office","OSM_ID":"2064362"}}
,{"type":"Feature","geometry":{"type":"Point","coordinates":[-111.9729793,42.2759123000001]},"properties":{"State":"ID","FCode":"78006","Feature":"Post Office","OSM_ID":"2064412"}}
,{"type":"Feature","geometry":{"type":"Point","coordinates":[-111.6831652,43.9673368000001]},"properties":{"State":"ID","FCode":"78006","Feature":"Post Office","OSM_ID":"2064545"}}
,{"type":"Feature","geometry":{"type":"Point","coordinates":[-112.0121303,42.6199367]},"properties":{"State":"ID","FCode":"78006","Feature":"Post Office","OSM_ID":"2064671"}}
,{"type":"Feature","geometry":{"type":"Point","coordinates":[-112.8758246,42.5733289]},"properties":{"State":"ID","FCode":"78006","Feature":"Post Office","OSM_ID":"2065073"}}
,{"type":"Feature","geometry":{"type":"Point","coordinates":[-111.4013427,42.1881312]},"properties":{"State":"ID","FCode":"78006","Feature":"Post Office","OSM_ID":"2065345"}}
,{"type":"Feature","geometry":{"type":"Point","coordinates":[-116.472438,44.5569769000001]},"properties":{"State":"ID","FCode":"78006","Feature":"Post Office","OSM_ID":"2065400"}}
,{"type":"Feature","geometry":{"type":"Point","coordinates":[-111.3685487,42.4732222000001]},"properties":{"State":"ID","FCode":"78006","Feature":"Post Office","OSM_ID":"2066055"}}
,{"type":"Feature","geometry":{"type":"Point","coordinates":[-116.3440581,43.6965835]},"properties":{"State":"ID","FCode":"78006","Feature":"Post Office","OSM_ID":"2066203"}}
,{"type":"Feature","geometry":{"type":"Point","coordinates":[-111.6030278,43.8855034000001]},"properties":{"State":"ID","FCode":"78006","Feature":"Post Office","OSM_ID":"2066380"}}
,{"type":"Feature","geometry":{"type":"Point","coordinates":[-116.7768212,47.6738286]},"properties":{"State":"ID","FCode":"78006","Feature":"Post Office","OSM_ID":"2066472"}}
,{"type":"Feature","geometry":{"type":"Point","coordinates":[-115.8071288,47.2508689000001]},"properties":{"State":"ID","FCode":"78006","Feature":"Post Office","OSM_ID":"2066647"}}
,{"type":"Feature","geometry":{"type":"Point","coordinates":[-116.2526523,46.4801901000001]},"properties":{"State":"ID","FCode":"78006","Feature":"Post Office","OSM_ID":"2066677"}}
,{"type":"Feature","geometry":{"type":"Point","coordinates":[-116.3298146,47.5489621]},"properties":{"State":"ID","FCode":"78006","Feature":"Post Office","OSM_ID":"2066715"}}
,{"type":"Feature","geometry":{"type":"Point","coordinates":[-115.4368409,45.8265045000001]},"properties":{"State":"ID","FCode":"78006","Feature":"Post Office","OSM_ID":"2066997"}}
,{"type":"Feature","geometry":{"type":"Point","coordinates":[-112.8375805,42.9440622000001]},"properties":{"State":"ID","FCode":"78006","Feature":"Post Office","OSM_ID":"2067103"}}
,{"type":"Feature","geometry":{"type":"Point","coordinates":[-114.4645304,42.5861031000001]},"properties":{"State":"ID","FCode":"78006","Feature":"Post Office","OSM_ID":"2067636"}}
,{"type":"Feature","geometry":{"type":"Point","coordinates":[-111.7303752,42.5767409000001]},"properties":{"State":"ID","FCode":"78006","Feature":"Post Office","OSM_ID":"2067714"}}
,{"type":"Feature","geometry":{"type":"Point","coordinates":[-116.2850133,43.6593161000001]},"properties":{"State":"ID","FCode":"78006","Feature":"Post Office","OSM_ID":"2067930"}}
,{"type":"Feature","geometry":{"type":"Point","coordinates":[-116.919389,44.0088829000001]},"properties":{"State":"ID","FCode":"78006","Feature":"Post Office","OSM_ID":"2067955"}}
,{"type":"Feature","geometry":{"type":"Point","coordinates":[-112.2433682,42.1875766000001]},"properties":{"State":"ID","FCode":"78006","Feature":"Post Office","OSM_ID":"2067968"}}
,{"type":"Feature","geometry":{"type":"Point","coordinates":[-116.1552159,43.5468040000001]},"properties":{"State":"ID","FCode":"78006","Feature":"Post Office","OSM_ID":"2068014"}}
,{"type":"Feature","geometry":{"type":"Point","coordinates":[-112.1837333,44.3587157000001]},"properties":{"State":"ID","FCode":"78006","Feature":"Post Office","OSM_ID":"2068614"}}
,{"type":"Feature","geometry":{"type":"Point","coordinates":[-112.4430708,42.8681551000001]},"properties":{"State":"ID","FCode":"78006","Feature":"Post Office","OSM_ID":"2068643"}}
,{"type":"Feature","geometry":{"type":"Point","coordinates":[-113.7813824,42.6078991000001]},"properties":{"State":"ID","FCode":"78006","Feature":"Post Office","OSM_ID":"2068663"}}
,{"type":"Feature","geometry":{"type":"Point","coordinates":[-114.4728841,42.5565326]},"properties":{"State":"ID","FCode":"78006","Feature":"Post Office","OSM_ID":"2068669"}}
,{"type":"Feature","geometry":{"type":"Point","coordinates":[-111.0642564,42.35848]},"properties":{"State":"ID","FCode":"78006","Feature":"Post Office","OSM_ID":"2069054"}}
,{"type":"Feature","geometry":{"type":"Point","coordinates":[-112.1758495,42.5617708]},"properties":{"State":"ID","FCode":"78006","Feature":"Post Office","OSM_ID":"2069149"}}
,{"type":"Feature","geometry":{"type":"Point","coordinates":[-112.8560816,42.7848777]},"properties":{"State":"ID","FCode":"78006","Feature":"Post Office","OSM_ID":"2069440"}}
,{"type":"Feature","geometry":{"type":"Point","coordinates":[-113.6123101,44.8482484]},"properties":{"State":"ID","FCode":"78006","Feature":"Post Office","OSM_ID":"2069928"}}
,{"type":"Feature","geometry":{"type":"Point","coordinates":[-113.891483,45.1756844000001]},"properties":{"State":"ID","FCode":"78006","Feature":"Post Office","OSM_ID":"2070172"}}
,{"type":"Feature","geometry":{"type":"Point","coordinates":[-116.9157112,47.7094352]},"properties":{"State":"ID","FCode":"78006","Feature":"Post Office","OSM_ID":"2070251"}}
,{"type":"Feature","geometry":{"type":"Point","coordinates":[-113.645642,44.9646222000001]},"properties":{"State":"ID","FCode":"78006","Feature":"Post Office","OSM_ID":"2070740"}}
,{"type":"Feature","geometry":{"type":"Point","coordinates":[-116.8000253,43.7259237000001]},"properties":{"State":"ID","FCode":"78006","Feature":"Post Office","OSM_ID":"2071078"}}
,{"type":"Feature","geometry":{"type":"Point","coordinates":[-116.728689,46.9179802]},"properties":{"State":"ID","FCode":"78006","Feature":"Post Office","OSM_ID":"2071531"}}
,{"type":"Feature","geometry":{"type":"Point","coordinates":[-113.6283135,42.5181149000001]},"properties":{"State":"ID","FCode":"78006","Feature":"Post Office","OSM_ID":"2071872"}}
,{"type":"Feature","geometry":{"type":"Point","coordinates":[-116.246726,43.6479605000001]},"properties":{"State":"ID","FCode":"78006","Feature":"Post Office","OSM_ID":"2072317"}}
,{"type":"Feature","geometry":{"type":"Point","coordinates":[-112.4372259,43.841368]},"properties":{"State":"ID","FCode":"78006","Feature":"Post Office","OSM_ID":"2072327"}}
,{"type":"Feature","geometry":{"type":"Point","coordinates":[-113.4887475,42.7533740000001]},"properties":{"State":"ID","FCode":"78006","Feature":"Post Office","OSM_ID":"2072397"}}
,{"type":"Feature","geometry":{"type":"Point","coordinates":[-112.1815622,43.3066628]},"properties":{"State":"ID","FCode":"78006","Feature":"Post Office","OSM_ID":"2072490"}}
,{"type":"Feature","geometry":{"type":"Point","coordinates":[-112.12779,43.7201985]},"properties":{"State":"ID","FCode":"78006","Feature":"Post Office","OSM_ID":"2072688"}}
,{"type":"Feature","geometry":{"type":"Point","coordinates":[-116.5507891,43.2164152]},"properties":{"State":"ID","FCode":"78006","Feature":"Post Office","OSM_ID":"2073045"}}
,{"type":"Feature","geometry":{"type":"Point","coordinates":[-113.3580333,44.6806570000001]},"properties":{"State":"ID","FCode":"78006","Feature":"Post Office","OSM_ID":"2073118"}}
,{"type":"Feature","geometry":{"type":"Point","coordinates":[-111.1601949,43.8137868000001]},"properties":{"State":"ID","FCode":"78006","Feature":"Post Office","OSM_ID":"2073477"}}
,{"type":"Feature","geometry":{"type":"Point","coordinates":[-114.2110073,42.6056630000001]},"properties":{"State":"ID","FCode":"78006","Feature":"Post Office","OSM_ID":"2073657"}}
,{"type":"Feature","geometry":{"type":"Point","coordinates":[-111.5971093,42.6546097]},"properties":{"State":"ID","FCode":"78006","Feature":"Post Office","OSM_ID":"2073675"}}
,{"type":"Feature","geometry":{"type":"Point","coordinates":[-114.5174649,42.7251261000001]},"properties":{"State":"ID","FCode":"78006","Feature":"Post Office","OSM_ID":"2073841"}}
,{"type":"Feature","geometry":{"type":"Point","coordinates":[-114.8723197,42.5206020000001]},"properties":{"State":"ID","FCode":"78006","Feature":"Post Office","OSM_ID":"2073962"}}
,{"type":"Feature","geometry":{"type":"Point","coordinates":[-112.4505569,42.8620674000001]},"properties":{"State":"ID","FCode":"78006","Feature":"Post Office","OSM_ID":"2074124"}}
,{"type":"Feature","geometry":{"type":"Point","coordinates":[-111.1111071,43.7235597000001]},"properties":{"State":"ID","FCode":"78006","Feature":"Post Office","OSM_ID":"2074173"}}
,{"type":"Feature","geometry":{"type":"Point","coordinates":[-111.8751451,42.0963116]},"properties":{"State":"ID","FCode":"78006","Feature":"Post Office","OSM_ID":"2074328"}}
,{"type":"Feature","geometry":{"type":"Point","coordinates":[-111.5737019,43.9988025000001]},"properties":{"State":"ID","FCode":"78006","Feature":"Post Office","OSM_ID":"2074329"}}
,{"type":"Feature","geometry":{"type":"Point","coordinates":[-112.003696,42.1861616]},"properties":{"State":"ID","FCode":"78006","Feature":"Post Office","OSM_ID":"2074475"}}
,{"type":"Feature","geometry":{"type":"Point","coordinates":[-116.9005294,46.9203245]},"properties":{"State":"ID","FCode":"78006","Feature":"Post Office","OSM_ID":"2074581"}}
,{"type":"Feature","geometry":{"type":"Point","coordinates":[-115.9547872,47.4928034000001]},"properties":{"State":"ID","FCode":"78006","Feature":"Post Office","OSM_ID":"2074692"}}
,{"type":"Feature","geometry":{"type":"Point","coordinates":[-116.8365251,46.9136974]},"properties":{"State":"ID","FCode":"78006","Feature":"Post Office","OSM_ID":"2074894"}}
,{"type":"Feature","geometry":{"type":"Point","coordinates":[-117.0240234,46.8394822000001]},"properties":{"State":"ID","FCode":"78006","Feature":"Post Office","OSM_ID":"2074972"}}
,{"type":"Feature","geometry":{"type":"Point","coordinates":[-116.2309509,43.872896]},"properties":{"State":"ID","FCode":"78006","Feature":"Post Office","OSM_ID":"2075006"}}
,{"type":"Feature","geometry":{"type":"Point","coordinates":[-115.8380711,43.8240557]},"properties":{"State":"ID","FCode":"78006","Feature":"Post Office","OSM_ID":"2075111"}}
,{"type":"Feature","geometry":{"type":"Point","coordinates":[-114.7581389,42.6001676000001]},"properties":{"State":"ID","FCode":"78006","Feature":"Post Office","OSM_ID":"2075215"}}
,{"type":"Feature","geometry":{"type":"Point","coordinates":[-112.595734,43.1178803000001]},"properties":{"State":"ID","FCode":"78006","Feature":"Post Office","OSM_ID":"2075555"}}
,{"type":"Feature","geometry":{"type":"Point","coordinates":[-111.3887971,42.1152772]},"properties":{"State":"ID","FCode":"78006","Feature":"Post Office","OSM_ID":"2076020"}}
,{"type":"Feature","geometry":{"type":"Point","coordinates":[-116.1777461,47.5435098]},"properties":{"State":"ID","FCode":"78006","Feature":"Post Office","OSM_ID":"2076216"}}
,{"type":"Feature","geometry":{"type":"Point","coordinates":[-116.4887049,43.6920064]},"properties":{"State":"ID","FCode":"78006","Feature":"Post Office","OSM_ID":"2076382"}}
,{"type":"Feature","geometry":{"type":"Point","coordinates":[-111.7271198,42.4086594]},"properties":{"State":"ID","FCode":"78006","Feature":"Post Office","OSM_ID":"2076889"}}
,{"type":"Feature","geometry":{"type":"Point","coordinates":[-111.6707271,43.886581]},"properties":{"State":"ID","FCode":"78006","Feature":"Post Office","OSM_ID":"2077276"}}
,{"type":"Feature","geometry":{"type":"Point","coordinates":[-115.8552169,47.6265908]},"properties":{"State":"ID","FCode":"78006","Feature":"Post Office","OSM_ID":"2077827"}}
,{"type":"Feature","geometry":{"type":"Point","coordinates":[-116.201423,43.6168757]},"properties":{"State":"ID","FCode":"78006","Feature":"Post Office","OSM_ID":"2078509"}}
,{"type":"Feature","geometry":{"type":"Point","coordinates":[-114.5941328,42.2201711000001]},"properties":{"State":"ID","FCode":"78006","Feature":"Post Office","OSM_ID":"2078549"}}
,{"type":"Feature","geometry":{"type":"Point","coordinates":[-112.2016541,43.9278487]},"properties":{"State":"ID","FCode":"78006","Feature":"Post Office","OSM_ID":"2078957"}}
,{"type":"Feature","geometry":{"type":"Point","coordinates":[-116.2532768,47.0114390000001]},"properties":{"State":"ID","FCode":"78006","Feature":"Post Office","OSM_ID":"2078965"}}
,{"type":"Feature","geometry":{"type":"Point","coordinates":[-111.3359924,43.4485259000001]},"properties":{"State":"ID","FCode":"78006","Feature":"Post Office","OSM_ID":"2079387"}}
,{"type":"Feature","geometry":{"type":"Point","coordinates":[-116.946268,43.7833205000001]},"properties":{"State":"ID","FCode":"78006","Feature":"Post Office","OSM_ID":"2079899"}}
,{"type":"Feature","geometry":{"type":"Point","coordinates":[-111.4009421,42.2289673000001]},"properties":{"State":"ID","FCode":"78006","Feature":"Post Office","OSM_ID":"2079989"}}
,{"type":"Feature","geometry":{"type":"Point","coordinates":[-116.201185,43.5825895]},"properties":{"State":"ID","FCode":"78006","Feature":"Post Office","OSM_ID":"2080086"}}
,{"type":"Feature","geometry":{"type":"Point","coordinates":[-113.945849,43.3094752000001]},"properties":{"State":"ID","FCode":"78006","Feature":"Post Office","OSM_ID":"2080400"}}
,{"type":"Feature","geometry":{"type":"Point","coordinates":[-116.1214358,47.5346616]},"properties":{"State":"ID","FCode":"78006","Feature":"Post Office","OSM_ID":"2080721"}}
,{"type":"Feature","geometry":{"type":"Point","coordinates":[-111.3070528,42.3188927]},"properties":{"State":"ID","FCode":"78006","Feature":"Post Office","OSM_ID":"2080915"}}
,{"type":"Feature","geometry":{"type":"Point","coordinates":[-112.5596552,42.5705803000001]},"properties":{"State":"ID","FCode":"78006","Feature":"Post Office","OSM_ID":"2080920"}}
,{"type":"Feature","geometry":{"type":"Point","coordinates":[-112.1918366,42.6487861000001]},"properties":{"State":"ID","FCode":"78006","Feature":"Post Office","OSM_ID":"2080935"}}
,{"type":"Feature","geometry":{"type":"Point","coordinates":[-117.0068521,46.7284679000001]},"properties":{"State":"ID","FCode":"78006","Feature":"Post Office","OSM_ID":"2081452"}}
]}
